{"title":"Asako","coverImageUrl":"https://i.truyenvua.com/ebook/190x247/asako_1583891125.jpg?gt=hdfgdfg&mobile=2","description":"\"Asako\" miêu tả mối quan hệ giữa một cậu bé 11 tuổi sống ở một làng chài ven biển, Masashi Aoshima, với một người đẹp bí ẩn, Asako, đến ở tại nhà trọ của cậu ấy từ Tokyo.","link":"https://truyenqqviet.com/truyen-tranh/asako-9149","chapters":[{"order":28,"name":"Chương 28","content":[{"order":1,"image":"https://s135.hinhhinh.com/9149/28/0.jpg?gt=hdfgdfg"},{"order":2,"image":"https://s135.hinhhinh.com/9149/28/1.jpg?gt=hdfgdfg"},{"order":3,"image":"https://s135.hinhhinh.com/9149/28/2.jpg?gt=hdfgdfg"},{"order":4,"image":"https://s135.hinhhinh.com/9149/28/3.jpg?gt=hdfgdfg"},{"order":5,"image":"https://s135.hinhhinh.com/9149/28/4.jpg?gt=hdfgdfg"},{"order":6,"image":"https://s135.hinhhinh.com/9149/28/5.jpg?gt=hdfgdfg"},{"order":7,"image":"https://s135.hinhhinh.com/9149/28/6.jpg?gt=hdfgdfg"},{"order":8,"image":"https://s135.hinhhinh.com/9149/28/7.jpg?gt=hdfgdfg"},{"order":9,"image":"https://s135.hinhhinh.com/9149/28/8.jpg?gt=hdfgdfg"},{"order":10,"image":"https://s135.hinhhinh.com/9149/28/9.jpg?gt=hdfgdfg"},{"order":11,"image":"https://s135.hinhhinh.com/9149/28/10.jpg?gt=hdfgdfg"},{"order":12,"image":"https://s135.hinhhinh.com/9149/28/11.jpg?gt=hdfgdfg"},{"order":13,"image":"https://s135.hinhhinh.com/9149/28/12.jpg?gt=hdfgdfg"},{"order":14,"image":"https://s135.hinhhinh.com/9149/28/13.jpg?gt=hdfgdfg"},{"order":15,"image":"https://s135.hinhhinh.com/9149/28/14.jpg?gt=hdfgdfg"},{"order":16,"image":"https://s135.hinhhinh.com/9149/28/15.jpg?gt=hdfgdfg"},{"order":17,"image":"https://s135.hinhhinh.com/9149/28/16.jpg?gt=hdfgdfg"},{"order":18,"image":"https://s135.hinhhinh.com/9149/28/17.jpg?gt=hdfgdfg"},{"order":19,"image":"https://s135.hinhhinh.com/9149/28/18.jpg?gt=hdfgdfg"},{"order":20,"image":"https://s135.hinhhinh.com/9149/28/19.jpg?gt=hdfgdfg"},{"order":21,"image":"https://s135.hinhhinh.com/9149/28/20.jpg?gt=hdfgdfg"},{"order":22,"image":"https://s135.hinhhinh.com/9149/28/21.jpg?gt=hdfgdfg"},{"order":23,"image":"https://s135.hinhhinh.com/9149/28/22.jpg?gt=hdfgdfg"},{"order":24,"image":"https://s135.hinhhinh.com/9149/28/23.jpg?gt=hdfgdfg"},{"order":25,"image":"https://s135.hinhhinh.com/9149/28/24.jpg?gt=hdfgdfg"},{"order":26,"image":"https://s135.hinhhinh.com/9149/28/25.jpg?gt=hdfgdfg"},{"order":27,"image":"https://s135.hinhhinh.com/9149/28/26.jpg?gt=hdfgdfg"},{"order":28,"image":"https://s135.hinhhinh.com/9149/28/27.jpg?gt=hdfgdfg"},{"order":29,"image":"https://s135.hinhhinh.com/9149/28/28.jpg?gt=hdfgdfg"},{"order":30,"image":"https://s135.hinhhinh.com/9149/28/29.jpg?gt=hdfgdfg"},{"order":31,"image":"https://s135.hinhhinh.com/9149/28/30.jpg?gt=hdfgdfg"},{"order":32,"image":"https://s135.hinhhinh.com/9149/28/31.jpg?gt=hdfgdfg"}]},{"order":27,"name":"Chương 27","content":[{"order":1,"image":"https://s135.hinhhinh.com/9149/27/0_ibqhm.jpg?gt=hdfgdfg"},{"order":2,"image":"https://s135.hinhhinh.com/9149/27/1_ik9i4.jpg?gt=hdfgdfg"},{"order":3,"image":"https://s135.hinhhinh.com/9149/27/2_qk64p.jpg?gt=hdfgdfg"},{"order":4,"image":"https://s135.hinhhinh.com/9149/27/3_v1qrx.jpg?gt=hdfgdfg"},{"order":5,"image":"https://s135.hinhhinh.com/9149/27/4_u14b5.jpg?gt=hdfgdfg"},{"order":6,"image":"https://s135.hinhhinh.com/9149/27/5_d1pe3.jpg?gt=hdfgdfg"},{"order":7,"image":"https://s135.hinhhinh.com/9149/27/6_k5owr.jpg?gt=hdfgdfg"},{"order":8,"image":"https://s135.hinhhinh.com/9149/27/7_5z7bv.jpg?gt=hdfgdfg"},{"order":9,"image":"https://s135.hinhhinh.com/9149/27/8_ht9mj.jpg?gt=hdfgdfg"},{"order":10,"image":"https://s135.hinhhinh.com/9149/27/9_5nvjp.jpg?gt=hdfgdfg"},{"order":11,"image":"https://s135.hinhhinh.com/9149/27/10_gs3ea.jpg?gt=hdfgdfg"},{"order":12,"image":"https://s135.hinhhinh.com/9149/27/11_tshyw.jpg?gt=hdfgdfg"},{"order":13,"image":"https://s135.hinhhinh.com/9149/27/12_az84h.jpg?gt=hdfgdfg"},{"order":14,"image":"https://s135.hinhhinh.com/9149/27/13_gwj9x.jpg?gt=hdfgdfg"},{"order":15,"image":"https://s135.hinhhinh.com/9149/27/14_xfad5.jpg?gt=hdfgdfg"},{"order":16,"image":"https://s135.hinhhinh.com/9149/27/15_f60df.jpg?gt=hdfgdfg"},{"order":17,"image":"https://s135.hinhhinh.com/9149/27/16_u09f5.jpg?gt=hdfgdfg"},{"order":18,"image":"https://s135.hinhhinh.com/9149/27/17_b6nse.jpg?gt=hdfgdfg"},{"order":19,"image":"https://s135.hinhhinh.com/9149/27/18_j30qa.jpg?gt=hdfgdfg"},{"order":20,"image":"https://s135.hinhhinh.com/9149/27/19_vhjgq.jpg?gt=hdfgdfg"},{"order":21,"image":"https://s135.hinhhinh.com/9149/27/20_enkec.jpg?gt=hdfgdfg"},{"order":22,"image":"https://s135.hinhhinh.com/9149/27/21_srl9x.jpg?gt=hdfgdfg"},{"order":23,"image":"https://s135.hinhhinh.com/9149/27/22_308nf.jpg?gt=hdfgdfg"},{"order":24,"image":"https://s135.hinhhinh.com/9149/27/23_yhepg.jpg?gt=hdfgdfg"},{"order":25,"image":"https://s135.hinhhinh.com/9149/27/24_d7fna.jpg?gt=hdfgdfg"}]},{"order":26,"name":"Chương 26","content":[{"order":1,"image":"https://s135.hinhhinh.com/9149/26/0.jpg?gt=hdfgdfg"},{"order":2,"image":"https://s135.hinhhinh.com/9149/26/1.jpg?gt=hdfgdfg"},{"order":3,"image":"https://s135.hinhhinh.com/9149/26/2.jpg?gt=hdfgdfg"},{"order":4,"image":"https://s135.hinhhinh.com/9149/26/3.jpg?gt=hdfgdfg"},{"order":5,"image":"https://s135.hinhhinh.com/9149/26/4.jpg?gt=hdfgdfg"},{"order":6,"image":"https://s135.hinhhinh.com/9149/26/5.jpg?gt=hdfgdfg"},{"order":7,"image":"https://s135.hinhhinh.com/9149/26/6.jpg?gt=hdfgdfg"},{"order":8,"image":"https://s135.hinhhinh.com/9149/26/7.jpg?gt=hdfgdfg"},{"order":9,"image":"https://s135.hinhhinh.com/9149/26/8.jpg?gt=hdfgdfg"},{"order":10,"image":"https://s135.hinhhinh.com/9149/26/9.jpg?gt=hdfgdfg"},{"order":11,"image":"https://s135.hinhhinh.com/9149/26/10.jpg?gt=hdfgdfg"},{"order":12,"image":"https://s135.hinhhinh.com/9149/26/11.jpg?gt=hdfgdfg"},{"order":13,"image":"https://s135.hinhhinh.com/9149/26/12.jpg?gt=hdfgdfg"},{"order":14,"image":"https://s135.hinhhinh.com/9149/26/13.jpg?gt=hdfgdfg"},{"order":15,"image":"https://s135.hinhhinh.com/9149/26/14.jpg?gt=hdfgdfg"},{"order":16,"image":"https://s135.hinhhinh.com/9149/26/15.jpg?gt=hdfgdfg"},{"order":17,"image":"https://s135.hinhhinh.com/9149/26/16.jpg?gt=hdfgdfg"},{"order":18,"image":"https://s135.hinhhinh.com/9149/26/17.jpg?gt=hdfgdfg"},{"order":19,"image":"https://s135.hinhhinh.com/9149/26/18.jpg?gt=hdfgdfg"},{"order":20,"image":"https://s135.hinhhinh.com/9149/26/19.jpg?gt=hdfgdfg"},{"order":21,"image":"https://s135.hinhhinh.com/9149/26/20.jpg?gt=hdfgdfg"},{"order":22,"image":"https://s135.hinhhinh.com/9149/26/21.jpg?gt=hdfgdfg"},{"order":23,"image":"https://s135.hinhhinh.com/9149/26/22.jpg?gt=hdfgdfg"},{"order":24,"image":"https://s135.hinhhinh.com/9149/26/23.jpg?gt=hdfgdfg"},{"order":25,"image":"https://s135.hinhhinh.com/9149/26/24.jpg?gt=hdfgdfg"},{"order":26,"image":"https://s135.hinhhinh.com/9149/26/25.jpg?gt=hdfgdfg"},{"order":27,"image":"https://s135.hinhhinh.com/9149/26/26.jpg?gt=hdfgdfg"},{"order":28,"image":"https://s135.hinhhinh.com/9149/26/27.jpg?gt=hdfgdfg"},{"order":29,"image":"https://s135.hinhhinh.com/9149/26/28.jpg?gt=hdfgdfg"},{"order":30,"image":"https://s135.hinhhinh.com/9149/26/29.jpg?gt=hdfgdfg"}]},{"order":25,"name":"Chương 25","content":[{"order":1,"image":"https://s135.hinhhinh.com/9149/25/0.jpg?gt=hdfgdfg"},{"order":2,"image":"https://s135.hinhhinh.com/9149/25/1.jpg?gt=hdfgdfg"},{"order":3,"image":"https://s135.hinhhinh.com/9149/25/2.jpg?gt=hdfgdfg"},{"order":4,"image":"https://s135.hinhhinh.com/9149/25/3.jpg?gt=hdfgdfg"},{"order":5,"image":"https://s135.hinhhinh.com/9149/25/4.jpg?gt=hdfgdfg"},{"order":6,"image":"https://s135.hinhhinh.com/9149/25/5.jpg?gt=hdfgdfg"},{"order":7,"image":"https://s135.hinhhinh.com/9149/25/6.jpg?gt=hdfgdfg"},{"order":8,"image":"https://s135.hinhhinh.com/9149/25/7.jpg?gt=hdfgdfg"},{"order":9,"image":"https://s135.hinhhinh.com/9149/25/8.jpg?gt=hdfgdfg"},{"order":10,"image":"https://s135.hinhhinh.com/9149/25/9.jpg?gt=hdfgdfg"},{"order":11,"image":"https://s135.hinhhinh.com/9149/25/10.jpg?gt=hdfgdfg"},{"order":12,"image":"https://s135.hinhhinh.com/9149/25/11.jpg?gt=hdfgdfg"},{"order":13,"image":"https://s135.hinhhinh.com/9149/25/12.jpg?gt=hdfgdfg"},{"order":14,"image":"https://s135.hinhhinh.com/9149/25/13.jpg?gt=hdfgdfg"},{"order":15,"image":"https://s135.hinhhinh.com/9149/25/14.jpg?gt=hdfgdfg"},{"order":16,"image":"https://s135.hinhhinh.com/9149/25/15.jpg?gt=hdfgdfg"},{"order":17,"image":"https://s135.hinhhinh.com/9149/25/16.jpg?gt=hdfgdfg"},{"order":18,"image":"https://s135.hinhhinh.com/9149/25/17.jpg?gt=hdfgdfg"},{"order":19,"image":"https://s135.hinhhinh.com/9149/25/18.jpg?gt=hdfgdfg"},{"order":20,"image":"https://s135.hinhhinh.com/9149/25/19.jpg?gt=hdfgdfg"},{"order":21,"image":"https://s135.hinhhinh.com/9149/25/20.jpg?gt=hdfgdfg"},{"order":22,"image":"https://s135.hinhhinh.com/9149/25/21.jpg?gt=hdfgdfg"},{"order":23,"image":"https://s135.hinhhinh.com/9149/25/22.jpg?gt=hdfgdfg"},{"order":24,"image":"https://s135.hinhhinh.com/9149/25/23.jpg?gt=hdfgdfg"}]},{"order":24,"name":"Chương 24","content":[{"order":1,"image":"https://truyenvua.com/9149/24/0.jpg?gt=hdfgdfg"},{"order":2,"image":"https://truyenvua.com/9149/24/1.jpg?gt=hdfgdfg"},{"order":3,"image":"https://truyenvua.com/9149/24/2.jpg?gt=hdfgdfg"},{"order":4,"image":"https://truyenvua.com/9149/24/3.jpg?gt=hdfgdfg"},{"order":5,"image":"https://truyenvua.com/9149/24/4.jpg?gt=hdfgdfg"},{"order":6,"image":"https://truyenvua.com/9149/24/5.jpg?gt=hdfgdfg"},{"order":7,"image":"https://truyenvua.com/9149/24/6.jpg?gt=hdfgdfg"},{"order":8,"image":"https://truyenvua.com/9149/24/7.jpg?gt=hdfgdfg"},{"order":9,"image":"https://truyenvua.com/9149/24/8.jpg?gt=hdfgdfg"},{"order":10,"image":"https://truyenvua.com/9149/24/9.jpg?gt=hdfgdfg"},{"order":11,"image":"https://truyenvua.com/9149/24/10.jpg?gt=hdfgdfg"},{"order":12,"image":"https://truyenvua.com/9149/24/11.jpg?gt=hdfgdfg"},{"order":13,"image":"https://truyenvua.com/9149/24/12.jpg?gt=hdfgdfg"},{"order":14,"image":"https://truyenvua.com/9149/24/13.jpg?gt=hdfgdfg"},{"order":15,"image":"https://truyenvua.com/9149/24/14.jpg?gt=hdfgdfg"},{"order":16,"image":"https://truyenvua.com/9149/24/15.jpg?gt=hdfgdfg"},{"order":17,"image":"https://truyenvua.com/9149/24/16.jpg?gt=hdfgdfg"},{"order":18,"image":"https://truyenvua.com/9149/24/17.jpg?gt=hdfgdfg"},{"order":19,"image":"https://truyenvua.com/9149/24/18.jpg?gt=hdfgdfg"},{"order":20,"image":"https://truyenvua.com/9149/24/19.jpg?gt=hdfgdfg"},{"order":21,"image":"https://truyenvua.com/9149/24/20.jpg?gt=hdfgdfg"},{"order":22,"image":"https://truyenvua.com/9149/24/21.jpg?gt=hdfgdfg"},{"order":23,"image":"https://truyenvua.com/9149/24/22.jpg?gt=hdfgdfg"},{"order":24,"image":"https://truyenvua.com/9149/24/23.jpg?gt=hdfgdfg"},{"order":25,"image":"https://truyenvua.com/9149/24/24.jpg?gt=hdfgdfg"},{"order":26,"image":"https://truyenvua.com/9149/24/25.jpg?gt=hdfgdfg"},{"order":27,"image":"https://truyenvua.com/9149/24/26.jpg?gt=hdfgdfg"},{"order":28,"image":"https://truyenvua.com/9149/24/27.jpg?gt=hdfgdfg"},{"order":29,"image":"https://truyenvua.com/9149/24/28.jpg?gt=hdfgdfg"},{"order":30,"image":"https://truyenvua.com/9149/24/29.jpg?gt=hdfgdfg"},{"order":31,"image":"https://truyenvua.com/9149/24/30.jpg?gt=hdfgdfg"},{"order":32,"image":"https://truyenvua.com/9149/24/31.jpg?gt=hdfgdfg"},{"order":33,"image":"https://truyenvua.com/9149/24/32.jpg?gt=hdfgdfg"},{"order":34,"image":"https://truyenvua.com/9149/24/33.jpg?gt=hdfgdfg"}]},{"order":23,"name":"Chương 23","content":[{"order":1,"image":"https://truyenvua.com/9149/23/0.jpg?gt=hdfgdfg"},{"order":2,"image":"https://truyenvua.com/9149/23/1.jpg?gt=hdfgdfg"},{"order":3,"image":"https://truyenvua.com/9149/23/2.jpg?gt=hdfgdfg"},{"order":4,"image":"https://truyenvua.com/9149/23/3.jpg?gt=hdfgdfg"},{"order":5,"image":"https://truyenvua.com/9149/23/4.jpg?gt=hdfgdfg"},{"order":6,"image":"https://truyenvua.com/9149/23/5.jpg?gt=hdfgdfg"},{"order":7,"image":"https://truyenvua.com/9149/23/6.jpg?gt=hdfgdfg"},{"order":8,"image":"https://truyenvua.com/9149/23/7.jpg?gt=hdfgdfg"},{"order":9,"image":"https://truyenvua.com/9149/23/8.jpg?gt=hdfgdfg"},{"order":10,"image":"https://truyenvua.com/9149/23/9.jpg?gt=hdfgdfg"},{"order":11,"image":"https://truyenvua.com/9149/23/10.jpg?gt=hdfgdfg"},{"order":12,"image":"https://truyenvua.com/9149/23/11.jpg?gt=hdfgdfg"},{"order":13,"image":"https://truyenvua.com/9149/23/12.jpg?gt=hdfgdfg"},{"order":14,"image":"https://truyenvua.com/9149/23/13.jpg?gt=hdfgdfg"},{"order":15,"image":"https://truyenvua.com/9149/23/14.jpg?gt=hdfgdfg"},{"order":16,"image":"https://truyenvua.com/9149/23/15.jpg?gt=hdfgdfg"},{"order":17,"image":"https://truyenvua.com/9149/23/16.jpg?gt=hdfgdfg"},{"order":18,"image":"https://truyenvua.com/9149/23/17.jpg?gt=hdfgdfg"},{"order":19,"image":"https://truyenvua.com/9149/23/18.jpg?gt=hdfgdfg"},{"order":20,"image":"https://truyenvua.com/9149/23/19.jpg?gt=hdfgdfg"},{"order":21,"image":"https://truyenvua.com/9149/23/20.jpg?gt=hdfgdfg"},{"order":22,"image":"https://truyenvua.com/9149/23/21.jpg?gt=hdfgdfg"},{"order":23,"image":"https://truyenvua.com/9149/23/22.jpg?gt=hdfgdfg"},{"order":24,"image":"https://truyenvua.com/9149/23/23.jpg?gt=hdfgdfg"},{"order":25,"image":"https://truyenvua.com/9149/23/24.jpg?gt=hdfgdfg"},{"order":26,"image":"https://truyenvua.com/9149/23/25.jpg?gt=hdfgdfg"},{"order":27,"image":"https://truyenvua.com/9149/23/26.jpg?gt=hdfgdfg"},{"order":28,"image":"https://truyenvua.com/9149/23/27.jpg?gt=hdfgdfg"},{"order":29,"image":"https://truyenvua.com/9149/23/28.jpg?gt=hdfgdfg"}]},{"order":22,"name":"Chương 22","content":[{"order":1,"image":"https://truyenvua.com/9149/22/0.jpg?gt=hdfgdfg"},{"order":2,"image":"https://truyenvua.com/9149/22/1.jpg?gt=hdfgdfg"},{"order":3,"image":"https://truyenvua.com/9149/22/2.jpg?gt=hdfgdfg"},{"order":4,"image":"https://truyenvua.com/9149/22/3.jpg?gt=hdfgdfg"},{"order":5,"image":"https://truyenvua.com/9149/22/4.jpg?gt=hdfgdfg"},{"order":6,"image":"https://truyenvua.com/9149/22/5.jpg?gt=hdfgdfg"},{"order":7,"image":"https://truyenvua.com/9149/22/6.jpg?gt=hdfgdfg"},{"order":8,"image":"https://truyenvua.com/9149/22/7.jpg?gt=hdfgdfg"},{"order":9,"image":"https://truyenvua.com/9149/22/8.jpg?gt=hdfgdfg"},{"order":10,"image":"https://truyenvua.com/9149/22/9.jpg?gt=hdfgdfg"},{"order":11,"image":"https://truyenvua.com/9149/22/10.jpg?gt=hdfgdfg"},{"order":12,"image":"https://truyenvua.com/9149/22/11.jpg?gt=hdfgdfg"},{"order":13,"image":"https://truyenvua.com/9149/22/12.jpg?gt=hdfgdfg"},{"order":14,"image":"https://truyenvua.com/9149/22/13.jpg?gt=hdfgdfg"},{"order":15,"image":"https://truyenvua.com/9149/22/14.jpg?gt=hdfgdfg"},{"order":16,"image":"https://truyenvua.com/9149/22/15.jpg?gt=hdfgdfg"},{"order":17,"image":"https://truyenvua.com/9149/22/16.jpg?gt=hdfgdfg"},{"order":18,"image":"https://truyenvua.com/9149/22/17.jpg?gt=hdfgdfg"},{"order":19,"image":"https://truyenvua.com/9149/22/18.jpg?gt=hdfgdfg"},{"order":20,"image":"https://truyenvua.com/9149/22/19.jpg?gt=hdfgdfg"},{"order":21,"image":"https://truyenvua.com/9149/22/20.jpg?gt=hdfgdfg"},{"order":22,"image":"https://truyenvua.com/9149/22/21.jpg?gt=hdfgdfg"},{"order":23,"image":"https://truyenvua.com/9149/22/22.jpg?gt=hdfgdfg"},{"order":24,"image":"https://truyenvua.com/9149/22/23.jpg?gt=hdfgdfg"},{"order":25,"image":"https://truyenvua.com/9149/22/24.jpg?gt=hdfgdfg"}]},{"order":21,"name":"Chương 21","content":[{"order":1,"image":"https://truyenvua.com/9149/21/0.jpg?gt=hdfgdfg"},{"order":2,"image":"https://truyenvua.com/9149/21/1.jpg?gt=hdfgdfg"},{"order":3,"image":"https://truyenvua.com/9149/21/2.jpg?gt=hdfgdfg"},{"order":4,"image":"https://truyenvua.com/9149/21/3.jpg?gt=hdfgdfg"},{"order":5,"image":"https://truyenvua.com/9149/21/4.jpg?gt=hdfgdfg"},{"order":6,"image":"https://truyenvua.com/9149/21/5.jpg?gt=hdfgdfg"},{"order":7,"image":"https://truyenvua.com/9149/21/6.jpg?gt=hdfgdfg"},{"order":8,"image":"https://truyenvua.com/9149/21/7.jpg?gt=hdfgdfg"},{"order":9,"image":"https://truyenvua.com/9149/21/8.jpg?gt=hdfgdfg"},{"order":10,"image":"https://truyenvua.com/9149/21/9.jpg?gt=hdfgdfg"},{"order":11,"image":"https://truyenvua.com/9149/21/10.jpg?gt=hdfgdfg"},{"order":12,"image":"https://truyenvua.com/9149/21/11.jpg?gt=hdfgdfg"},{"order":13,"image":"https://truyenvua.com/9149/21/12.jpg?gt=hdfgdfg"},{"order":14,"image":"https://truyenvua.com/9149/21/13.jpg?gt=hdfgdfg"},{"order":15,"image":"https://truyenvua.com/9149/21/14.jpg?gt=hdfgdfg"},{"order":16,"image":"https://truyenvua.com/9149/21/15.jpg?gt=hdfgdfg"},{"order":17,"image":"https://truyenvua.com/9149/21/16.jpg?gt=hdfgdfg"},{"order":18,"image":"https://truyenvua.com/9149/21/17.jpg?gt=hdfgdfg"},{"order":19,"image":"https://truyenvua.com/9149/21/18.jpg?gt=hdfgdfg"},{"order":20,"image":"https://truyenvua.com/9149/21/19.jpg?gt=hdfgdfg"},{"order":21,"image":"https://truyenvua.com/9149/21/20.jpg?gt=hdfgdfg"},{"order":22,"image":"https://truyenvua.com/9149/21/21.jpg?gt=hdfgdfg"},{"order":23,"image":"https://truyenvua.com/9149/21/22.jpg?gt=hdfgdfg"},{"order":24,"image":"https://truyenvua.com/9149/21/23.jpg?gt=hdfgdfg"},{"order":25,"image":"https://truyenvua.com/9149/21/24.jpg?gt=hdfgdfg"},{"order":26,"image":"https://truyenvua.com/9149/21/25.jpg?gt=hdfgdfg"},{"order":27,"image":"https://truyenvua.com/9149/21/26.jpg?gt=hdfgdfg"},{"order":28,"image":"https://truyenvua.com/9149/21/27.jpg?gt=hdfgdfg"},{"order":29,"image":"https://truyenvua.com/9149/21/28.jpg?gt=hdfgdfg"},{"order":30,"image":"https://truyenvua.com/9149/21/29.jpg?gt=hdfgdfg"},{"order":31,"image":"https://truyenvua.com/9149/21/30.jpg?gt=hdfgdfg"},{"order":32,"image":"https://truyenvua.com/9149/21/31.jpg?gt=hdfgdfg"},{"order":33,"image":"https://truyenvua.com/9149/21/32.jpg?gt=hdfgdfg"},{"order":34,"image":"https://truyenvua.com/9149/21/33.jpg?gt=hdfgdfg"},{"order":35,"image":"https://truyenvua.com/9149/21/34.jpg?gt=hdfgdfg"},{"order":36,"image":"https://truyenvua.com/9149/21/35.jpg?gt=hdfgdfg"},{"order":37,"image":"https://truyenvua.com/9149/21/36.jpg?gt=hdfgdfg"}]},{"order":20,"name":"Chương 20","content":[{"order":1,"image":"https://truyenvua.com/9149/20/0.jpg?gt=hdfgdfg"},{"order":2,"image":"https://truyenvua.com/9149/20/1.jpg?gt=hdfgdfg"},{"order":3,"image":"https://truyenvua.com/9149/20/2.jpg?gt=hdfgdfg"},{"order":4,"image":"https://truyenvua.com/9149/20/3.jpg?gt=hdfgdfg"},{"order":5,"image":"https://truyenvua.com/9149/20/4.jpg?gt=hdfgdfg"},{"order":6,"image":"https://truyenvua.com/9149/20/5.jpg?gt=hdfgdfg"},{"order":7,"image":"https://truyenvua.com/9149/20/6.jpg?gt=hdfgdfg"},{"order":8,"image":"https://truyenvua.com/9149/20/7.jpg?gt=hdfgdfg"},{"order":9,"image":"https://truyenvua.com/9149/20/8.jpg?gt=hdfgdfg"},{"order":10,"image":"https://truyenvua.com/9149/20/9.jpg?gt=hdfgdfg"},{"order":11,"image":"https://truyenvua.com/9149/20/10.jpg?gt=hdfgdfg"},{"order":12,"image":"https://truyenvua.com/9149/20/11.jpg?gt=hdfgdfg"},{"order":13,"image":"https://truyenvua.com/9149/20/12.jpg?gt=hdfgdfg"},{"order":14,"image":"https://truyenvua.com/9149/20/13.jpg?gt=hdfgdfg"},{"order":15,"image":"https://truyenvua.com/9149/20/14.jpg?gt=hdfgdfg"},{"order":16,"image":"https://truyenvua.com/9149/20/15.jpg?gt=hdfgdfg"},{"order":17,"image":"https://truyenvua.com/9149/20/16.jpg?gt=hdfgdfg"},{"order":18,"image":"https://truyenvua.com/9149/20/17.jpg?gt=hdfgdfg"},{"order":19,"image":"https://truyenvua.com/9149/20/18.jpg?gt=hdfgdfg"},{"order":20,"image":"https://truyenvua.com/9149/20/19.jpg?gt=hdfgdfg"},{"order":21,"image":"https://truyenvua.com/9149/20/20.jpg?gt=hdfgdfg"},{"order":22,"image":"https://truyenvua.com/9149/20/21.jpg?gt=hdfgdfg"},{"order":23,"image":"https://truyenvua.com/9149/20/22.jpg?gt=hdfgdfg"},{"order":24,"image":"https://truyenvua.com/9149/20/23.jpg?gt=hdfgdfg"},{"order":25,"image":"https://truyenvua.com/9149/20/24.jpg?gt=hdfgdfg"},{"order":26,"image":"https://truyenvua.com/9149/20/25.jpg?gt=hdfgdfg"},{"order":27,"image":"https://truyenvua.com/9149/20/26.jpg?gt=hdfgdfg"},{"order":28,"image":"https://truyenvua.com/9149/20/27.jpg?gt=hdfgdfg"},{"order":29,"image":"https://truyenvua.com/9149/20/28.jpg?gt=hdfgdfg"},{"order":30,"image":"https://truyenvua.com/9149/20/29.jpg?gt=hdfgdfg"},{"order":31,"image":"https://truyenvua.com/9149/20/30.jpg?gt=hdfgdfg"},{"order":32,"image":"https://truyenvua.com/9149/20/31.jpg?gt=hdfgdfg"}]},{"order":19,"name":"Chương 19","content":[{"order":1,"image":"https://truyenvua.com/9149/19/0.jpg?gt=hdfgdfg"},{"order":2,"image":"https://truyenvua.com/9149/19/1.jpg?gt=hdfgdfg"},{"order":3,"image":"https://truyenvua.com/9149/19/2.jpg?gt=hdfgdfg"},{"order":4,"image":"https://truyenvua.com/9149/19/3.jpg?gt=hdfgdfg"},{"order":5,"image":"https://truyenvua.com/9149/19/4.jpg?gt=hdfgdfg"},{"order":6,"image":"https://truyenvua.com/9149/19/5.jpg?gt=hdfgdfg"},{"order":7,"image":"https://truyenvua.com/9149/19/6.jpg?gt=hdfgdfg"},{"order":8,"image":"https://truyenvua.com/9149/19/7.jpg?gt=hdfgdfg"},{"order":9,"image":"https://truyenvua.com/9149/19/8.jpg?gt=hdfgdfg"},{"order":10,"image":"https://truyenvua.com/9149/19/9.jpg?gt=hdfgdfg"},{"order":11,"image":"https://truyenvua.com/9149/19/10.jpg?gt=hdfgdfg"},{"order":12,"image":"https://truyenvua.com/9149/19/11.jpg?gt=hdfgdfg"},{"order":13,"image":"https://truyenvua.com/9149/19/12.jpg?gt=hdfgdfg"},{"order":14,"image":"https://truyenvua.com/9149/19/13.jpg?gt=hdfgdfg"},{"order":15,"image":"https://truyenvua.com/9149/19/14.jpg?gt=hdfgdfg"},{"order":16,"image":"https://truyenvua.com/9149/19/15.jpg?gt=hdfgdfg"},{"order":17,"image":"https://truyenvua.com/9149/19/16.jpg?gt=hdfgdfg"},{"order":18,"image":"https://truyenvua.com/9149/19/17.jpg?gt=hdfgdfg"},{"order":19,"image":"https://truyenvua.com/9149/19/18.jpg?gt=hdfgdfg"},{"order":20,"image":"https://truyenvua.com/9149/19/19.jpg?gt=hdfgdfg"},{"order":21,"image":"https://truyenvua.com/9149/19/20.jpg?gt=hdfgdfg"},{"order":22,"image":"https://truyenvua.com/9149/19/21.jpg?gt=hdfgdfg"},{"order":23,"image":"https://truyenvua.com/9149/19/22.jpg?gt=hdfgdfg"},{"order":24,"image":"https://truyenvua.com/9149/19/23.jpg?gt=hdfgdfg"},{"order":25,"image":"https://truyenvua.com/9149/19/24.jpg?gt=hdfgdfg"},{"order":26,"image":"https://truyenvua.com/9149/19/25.jpg?gt=hdfgdfg"},{"order":27,"image":"https://truyenvua.com/9149/19/26.jpg?gt=hdfgdfg"},{"order":28,"image":"https://truyenvua.com/9149/19/27.jpg?gt=hdfgdfg"},{"order":29,"image":"https://truyenvua.com/9149/19/28.jpg?gt=hdfgdfg"},{"order":30,"image":"https://truyenvua.com/9149/19/29.jpg?gt=hdfgdfg"},{"order":31,"image":"https://truyenvua.com/9149/19/30.jpg?gt=hdfgdfg"},{"order":32,"image":"https://truyenvua.com/9149/19/31.jpg?gt=hdfgdfg"},{"order":33,"image":"https://truyenvua.com/9149/19/32.jpg?gt=hdfgdfg"},{"order":34,"image":"https://truyenvua.com/9149/19/33.jpg?gt=hdfgdfg"},{"order":35,"image":"https://truyenvua.com/9149/19/34.jpg?gt=hdfgdfg"},{"order":36,"image":"https://truyenvua.com/9149/19/35.jpg?gt=hdfgdfg"},{"order":37,"image":"https://truyenvua.com/9149/19/36.jpg?gt=hdfgdfg"}]},{"order":18,"name":"Chương 18","content":[{"order":1,"image":"https://hinhhinh.com/9149/18/0.jpg?gt=hdfgdfg"},{"order":2,"image":"https://hinhhinh.com/9149/18/1.jpg?gt=hdfgdfg"},{"order":3,"image":"https://hinhhinh.com/9149/18/2.jpg?gt=hdfgdfg"},{"order":4,"image":"https://hinhhinh.com/9149/18/3.jpg?gt=hdfgdfg"},{"order":5,"image":"https://hinhhinh.com/9149/18/4.jpg?gt=hdfgdfg"},{"order":6,"image":"https://hinhhinh.com/9149/18/5.jpg?gt=hdfgdfg"},{"order":7,"image":"https://hinhhinh.com/9149/18/6.jpg?gt=hdfgdfg"},{"order":8,"image":"https://hinhhinh.com/9149/18/7.jpg?gt=hdfgdfg"},{"order":9,"image":"https://hinhhinh.com/9149/18/8.jpg?gt=hdfgdfg"},{"order":10,"image":"https://hinhhinh.com/9149/18/9.jpg?gt=hdfgdfg"},{"order":11,"image":"https://hinhhinh.com/9149/18/10.jpg?gt=hdfgdfg"},{"order":12,"image":"https://hinhhinh.com/9149/18/11.jpg?gt=hdfgdfg"},{"order":13,"image":"https://hinhhinh.com/9149/18/12.jpg?gt=hdfgdfg"},{"order":14,"image":"https://hinhhinh.com/9149/18/13.jpg?gt=hdfgdfg"},{"order":15,"image":"https://hinhhinh.com/9149/18/14.jpg?gt=hdfgdfg"},{"order":16,"image":"https://hinhhinh.com/9149/18/15.jpg?gt=hdfgdfg"},{"order":17,"image":"https://hinhhinh.com/9149/18/16.jpg?gt=hdfgdfg"},{"order":18,"image":"https://hinhhinh.com/9149/18/17.jpg?gt=hdfgdfg"},{"order":19,"image":"https://hinhhinh.com/9149/18/18.jpg?gt=hdfgdfg"},{"order":20,"image":"https://hinhhinh.com/9149/18/19.jpg?gt=hdfgdfg"},{"order":21,"image":"https://hinhhinh.com/9149/18/20.jpg?gt=hdfgdfg"},{"order":22,"image":"https://hinhhinh.com/9149/18/21.jpg?gt=hdfgdfg"},{"order":23,"image":"https://hinhhinh.com/9149/18/22.jpg?gt=hdfgdfg"},{"order":24,"image":"https://hinhhinh.com/9149/18/23.jpg?gt=hdfgdfg"},{"order":25,"image":"https://hinhhinh.com/9149/18/24.jpg?gt=hdfgdfg"},{"order":26,"image":"https://hinhhinh.com/9149/18/25.jpg?gt=hdfgdfg"},{"order":27,"image":"https://hinhhinh.com/9149/18/26.jpg?gt=hdfgdfg"},{"order":28,"image":"https://hinhhinh.com/9149/18/27.jpg?gt=hdfgdfg"},{"order":29,"image":"https://hinhhinh.com/9149/18/28.jpg?gt=hdfgdfg"}]},{"order":17,"name":"Chương 17","content":[{"order":1,"image":"https://hinhhinh.com/9149/17/0.jpg?gt=hdfgdfg"},{"order":2,"image":"https://hinhhinh.com/9149/17/1.jpg?gt=hdfgdfg"},{"order":3,"image":"https://hinhhinh.com/9149/17/2.jpg?gt=hdfgdfg"},{"order":4,"image":"https://hinhhinh.com/9149/17/3.jpg?gt=hdfgdfg"},{"order":5,"image":"https://hinhhinh.com/9149/17/4.jpg?gt=hdfgdfg"},{"order":6,"image":"https://hinhhinh.com/9149/17/5.jpg?gt=hdfgdfg"},{"order":7,"image":"https://hinhhinh.com/9149/17/6.jpg?gt=hdfgdfg"},{"order":8,"image":"https://hinhhinh.com/9149/17/7.jpg?gt=hdfgdfg"},{"order":9,"image":"https://hinhhinh.com/9149/17/8.jpg?gt=hdfgdfg"},{"order":10,"image":"https://hinhhinh.com/9149/17/9.jpg?gt=hdfgdfg"},{"order":11,"image":"https://hinhhinh.com/9149/17/10.jpg?gt=hdfgdfg"},{"order":12,"image":"https://hinhhinh.com/9149/17/11.jpg?gt=hdfgdfg"},{"order":13,"image":"https://hinhhinh.com/9149/17/12.jpg?gt=hdfgdfg"},{"order":14,"image":"https://hinhhinh.com/9149/17/13.jpg?gt=hdfgdfg"},{"order":15,"image":"https://hinhhinh.com/9149/17/14.jpg?gt=hdfgdfg"},{"order":16,"image":"https://hinhhinh.com/9149/17/15.jpg?gt=hdfgdfg"},{"order":17,"image":"https://hinhhinh.com/9149/17/16.jpg?gt=hdfgdfg"},{"order":18,"image":"https://hinhhinh.com/9149/17/17.jpg?gt=hdfgdfg"},{"order":19,"image":"https://hinhhinh.com/9149/17/18.jpg?gt=hdfgdfg"},{"order":20,"image":"https://hinhhinh.com/9149/17/19.jpg?gt=hdfgdfg"},{"order":21,"image":"https://hinhhinh.com/9149/17/20.jpg?gt=hdfgdfg"},{"order":22,"image":"https://hinhhinh.com/9149/17/21.jpg?gt=hdfgdfg"},{"order":23,"image":"https://hinhhinh.com/9149/17/22.jpg?gt=hdfgdfg"},{"order":24,"image":"https://hinhhinh.com/9149/17/23.jpg?gt=hdfgdfg"},{"order":25,"image":"https://hinhhinh.com/9149/17/24.jpg?gt=hdfgdfg"},{"order":26,"image":"https://hinhhinh.com/9149/17/25.jpg?gt=hdfgdfg"}]},{"order":16,"name":"Chương 16","content":[{"order":1,"image":"https://hinhhinh.com/9149/16/0.jpg?gt=hdfgdfg"},{"order":2,"image":"https://hinhhinh.com/9149/16/1.jpg?gt=hdfgdfg"},{"order":3,"image":"https://hinhhinh.com/9149/16/2.jpg?gt=hdfgdfg"},{"order":4,"image":"https://hinhhinh.com/9149/16/3.jpg?gt=hdfgdfg"},{"order":5,"image":"https://hinhhinh.com/9149/16/4.jpg?gt=hdfgdfg"},{"order":6,"image":"https://hinhhinh.com/9149/16/5.jpg?gt=hdfgdfg"},{"order":7,"image":"https://hinhhinh.com/9149/16/6.jpg?gt=hdfgdfg"},{"order":8,"image":"https://hinhhinh.com/9149/16/7.jpg?gt=hdfgdfg"},{"order":9,"image":"https://hinhhinh.com/9149/16/8.jpg?gt=hdfgdfg"},{"order":10,"image":"https://hinhhinh.com/9149/16/9.jpg?gt=hdfgdfg"},{"order":11,"image":"https://hinhhinh.com/9149/16/10.jpg?gt=hdfgdfg"},{"order":12,"image":"https://hinhhinh.com/9149/16/11.jpg?gt=hdfgdfg"},{"order":13,"image":"https://hinhhinh.com/9149/16/12.jpg?gt=hdfgdfg"},{"order":14,"image":"https://hinhhinh.com/9149/16/13.jpg?gt=hdfgdfg"},{"order":15,"image":"https://hinhhinh.com/9149/16/14.jpg?gt=hdfgdfg"},{"order":16,"image":"https://hinhhinh.com/9149/16/15.jpg?gt=hdfgdfg"},{"order":17,"image":"https://hinhhinh.com/9149/16/16.jpg?gt=hdfgdfg"},{"order":18,"image":"https://hinhhinh.com/9149/16/17.jpg?gt=hdfgdfg"},{"order":19,"image":"https://hinhhinh.com/9149/16/18.jpg?gt=hdfgdfg"},{"order":20,"image":"https://hinhhinh.com/9149/16/19.jpg?gt=hdfgdfg"},{"order":21,"image":"https://hinhhinh.com/9149/16/20.jpg?gt=hdfgdfg"},{"order":22,"image":"https://hinhhinh.com/9149/16/21.jpg?gt=hdfgdfg"},{"order":23,"image":"https://hinhhinh.com/9149/16/22.jpg?gt=hdfgdfg"},{"order":24,"image":"https://hinhhinh.com/9149/16/23.jpg?gt=hdfgdfg"},{"order":25,"image":"https://hinhhinh.com/9149/16/24.jpg?gt=hdfgdfg"},{"order":26,"image":"https://hinhhinh.com/9149/16/25.jpg?gt=hdfgdfg"},{"order":27,"image":"https://hinhhinh.com/9149/16/26.jpg?gt=hdfgdfg"},{"order":28,"image":"https://hinhhinh.com/9149/16/27.jpg?gt=hdfgdfg"},{"order":29,"image":"https://hinhhinh.com/9149/16/28.jpg?gt=hdfgdfg"},{"order":30,"image":"https://hinhhinh.com/9149/16/29.jpg?gt=hdfgdfg"},{"order":31,"image":"https://hinhhinh.com/9149/16/30.jpg?gt=hdfgdfg"},{"order":32,"image":"https://hinhhinh.com/9149/16/31.jpg?gt=hdfgdfg"},{"order":33,"image":"https://hinhhinh.com/9149/16/32.jpg?gt=hdfgdfg"},{"order":34,"image":"https://hinhhinh.com/9149/16/33.jpg?gt=hdfgdfg"}]},{"order":15,"name":"Chương 15","content":[{"order":1,"image":"https://tintruyen.net/9149/15/0.jpg?d=dfgd6546"},{"order":2,"image":"https://tintruyen.net/9149/15/1.jpg?d=dfgd6546"},{"order":3,"image":"https://tintruyen.net/9149/15/2.jpg?d=dfgd6546"},{"order":4,"image":"https://tintruyen.net/9149/15/3.jpg?d=dfgd6546"},{"order":5,"image":"https://tintruyen.net/9149/15/4.jpg?d=dfgd6546"},{"order":6,"image":"https://tintruyen.net/9149/15/5.jpg?d=dfgd6546"},{"order":7,"image":"https://tintruyen.net/9149/15/6.jpg?d=dfgd6546"},{"order":8,"image":"https://tintruyen.net/9149/15/7.jpg?d=dfgd6546"},{"order":9,"image":"https://tintruyen.net/9149/15/8.jpg?d=dfgd6546"},{"order":10,"image":"https://tintruyen.net/9149/15/9.jpg?d=dfgd6546"},{"order":11,"image":"https://tintruyen.net/9149/15/10.jpg?d=dfgd6546"},{"order":12,"image":"https://tintruyen.net/9149/15/11.jpg?d=dfgd6546"},{"order":13,"image":"https://tintruyen.net/9149/15/12.jpg?d=dfgd6546"},{"order":14,"image":"https://tintruyen.net/9149/15/13.jpg?d=dfgd6546"},{"order":15,"image":"https://tintruyen.net/9149/15/14.jpg?d=dfgd6546"},{"order":16,"image":"https://tintruyen.net/9149/15/15.jpg?d=dfgd6546"},{"order":17,"image":"https://tintruyen.net/9149/15/16.jpg?d=dfgd6546"},{"order":18,"image":"https://tintruyen.net/9149/15/17.jpg?d=dfgd6546"},{"order":19,"image":"https://tintruyen.net/9149/15/18.jpg?d=dfgd6546"},{"order":20,"image":"https://tintruyen.net/9149/15/19.jpg?d=dfgd6546"},{"order":21,"image":"https://tintruyen.net/9149/15/20.jpg?d=dfgd6546"},{"order":22,"image":"https://tintruyen.net/9149/15/21.jpg?d=dfgd6546"},{"order":23,"image":"https://tintruyen.net/9149/15/22.jpg?d=dfgd6546"}]},{"order":14,"name":"Chương 14","content":[{"order":1,"image":"https://tintruyen.net/9149/14/0.jpg?d=dfgd6546"},{"order":2,"image":"https://tintruyen.net/9149/14/1.jpg?d=dfgd6546"},{"order":3,"image":"https://tintruyen.net/9149/14/2.jpg?d=dfgd6546"},{"order":4,"image":"https://tintruyen.net/9149/14/3.jpg?d=dfgd6546"},{"order":5,"image":"https://tintruyen.net/9149/14/4.jpg?d=dfgd6546"},{"order":6,"image":"https://tintruyen.net/9149/14/5.jpg?d=dfgd6546"},{"order":7,"image":"https://tintruyen.net/9149/14/6.jpg?d=dfgd6546"},{"order":8,"image":"https://tintruyen.net/9149/14/7.jpg?d=dfgd6546"},{"order":9,"image":"https://tintruyen.net/9149/14/8.jpg?d=dfgd6546"},{"order":10,"image":"https://tintruyen.net/9149/14/9.jpg?d=dfgd6546"},{"order":11,"image":"https://tintruyen.net/9149/14/10.jpg?d=dfgd6546"},{"order":12,"image":"https://tintruyen.net/9149/14/11.jpg?d=dfgd6546"},{"order":13,"image":"https://tintruyen.net/9149/14/12.jpg?d=dfgd6546"},{"order":14,"image":"https://tintruyen.net/9149/14/13.jpg?d=dfgd6546"},{"order":15,"image":"https://tintruyen.net/9149/14/14.jpg?d=dfgd6546"},{"order":16,"image":"https://tintruyen.net/9149/14/15.jpg?d=dfgd6546"},{"order":17,"image":"https://tintruyen.net/9149/14/16.jpg?d=dfgd6546"},{"order":18,"image":"https://tintruyen.net/9149/14/17.jpg?d=dfgd6546"},{"order":19,"image":"https://tintruyen.net/9149/14/18.jpg?d=dfgd6546"},{"order":20,"image":"https://tintruyen.net/9149/14/19.jpg?d=dfgd6546"},{"order":21,"image":"https://tintruyen.net/9149/14/20.jpg?d=dfgd6546"},{"order":22,"image":"https://tintruyen.net/9149/14/21.jpg?d=dfgd6546"},{"order":23,"image":"https://tintruyen.net/9149/14/22.jpg?d=dfgd6546"},{"order":24,"image":"https://tintruyen.net/9149/14/23.jpg?d=dfgd6546"},{"order":25,"image":"https://tintruyen.net/9149/14/24.jpg?d=dfgd6546"},{"order":26,"image":"https://tintruyen.net/9149/14/25.jpg?d=dfgd6546"},{"order":27,"image":"https://tintruyen.net/9149/14/26.jpg?d=dfgd6546"},{"order":28,"image":"https://tintruyen.net/9149/14/27.jpg?d=dfgd6546"},{"order":29,"image":"https://tintruyen.net/9149/14/28.jpg?d=dfgd6546"},{"order":30,"image":"https://tintruyen.net/9149/14/29.jpg?d=dfgd6546"},{"order":31,"image":"https://tintruyen.net/9149/14/30.jpg?d=dfgd6546"},{"order":32,"image":"https://tintruyen.net/9149/14/31.jpg?d=dfgd6546"},{"order":33,"image":"https://tintruyen.net/9149/14/32.jpg?d=dfgd6546"},{"order":34,"image":"https://tintruyen.net/9149/14/33.jpg?d=dfgd6546"},{"order":35,"image":"https://tintruyen.net/9149/14/34.jpg?d=dfgd6546"},{"order":36,"image":"https://tintruyen.net/9149/14/35.jpg?d=dfgd6546"},{"order":37,"image":"https://tintruyen.net/9149/14/36.jpg?d=dfgd6546"},{"order":38,"image":"https://tintruyen.net/9149/14/37.jpg?d=dfgd6546"},{"order":39,"image":"https://tintruyen.net/9149/14/38.jpg?d=dfgd6546"},{"order":40,"image":"https://tintruyen.net/9149/14/39.jpg?d=dfgd6546"},{"order":41,"image":"https://tintruyen.net/9149/14/40.jpg?d=dfgd6546"}]},{"order":13,"name":"Chương 13","content":[{"order":1,"image":"https://tintruyen.net/9149/13/0.jpg?d=dfgd6546"},{"order":2,"image":"https://tintruyen.net/9149/13/1.jpg?d=dfgd6546"},{"order":3,"image":"https://tintruyen.net/9149/13/2.jpg?d=dfgd6546"},{"order":4,"image":"https://tintruyen.net/9149/13/3.jpg?d=dfgd6546"},{"order":5,"image":"https://tintruyen.net/9149/13/4.jpg?d=dfgd6546"},{"order":6,"image":"https://tintruyen.net/9149/13/5.jpg?d=dfgd6546"},{"order":7,"image":"https://tintruyen.net/9149/13/6.jpg?d=dfgd6546"},{"order":8,"image":"https://tintruyen.net/9149/13/7.jpg?d=dfgd6546"},{"order":9,"image":"https://tintruyen.net/9149/13/8.jpg?d=dfgd6546"},{"order":10,"image":"https://tintruyen.net/9149/13/9.jpg?d=dfgd6546"},{"order":11,"image":"https://tintruyen.net/9149/13/10.jpg?d=dfgd6546"},{"order":12,"image":"https://tintruyen.net/9149/13/11.jpg?d=dfgd6546"},{"order":13,"image":"https://tintruyen.net/9149/13/12.jpg?d=dfgd6546"},{"order":14,"image":"https://tintruyen.net/9149/13/13.jpg?d=dfgd6546"},{"order":15,"image":"https://tintruyen.net/9149/13/14.jpg?d=dfgd6546"},{"order":16,"image":"https://tintruyen.net/9149/13/15.jpg?d=dfgd6546"},{"order":17,"image":"https://tintruyen.net/9149/13/16.jpg?d=dfgd6546"},{"order":18,"image":"https://tintruyen.net/9149/13/17.jpg?d=dfgd6546"},{"order":19,"image":"https://tintruyen.net/9149/13/18.jpg?d=dfgd6546"},{"order":20,"image":"https://tintruyen.net/9149/13/19.jpg?d=dfgd6546"},{"order":21,"image":"https://tintruyen.net/9149/13/20.jpg?d=dfgd6546"},{"order":22,"image":"https://tintruyen.net/9149/13/21.jpg?d=dfgd6546"},{"order":23,"image":"https://tintruyen.net/9149/13/22.jpg?d=dfgd6546"},{"order":24,"image":"https://tintruyen.net/9149/13/23.jpg?d=dfgd6546"},{"order":25,"image":"https://tintruyen.net/9149/13/24.jpg?d=dfgd6546"},{"order":26,"image":"https://tintruyen.net/9149/13/25.jpg?d=dfgd6546"},{"order":27,"image":"https://tintruyen.net/9149/13/26.jpg?d=dfgd6546"},{"order":28,"image":"https://tintruyen.net/9149/13/27.jpg?d=dfgd6546"},{"order":29,"image":"https://tintruyen.net/9149/13/28.jpg?d=dfgd6546"},{"order":30,"image":"https://tintruyen.net/9149/13/29.jpg?d=dfgd6546"},{"order":31,"image":"https://tintruyen.net/9149/13/30.jpg?d=dfgd6546"},{"order":32,"image":"https://tintruyen.net/9149/13/31.jpg?d=dfgd6546"},{"order":33,"image":"https://tintruyen.net/9149/13/32.jpg?d=dfgd6546"},{"order":34,"image":"https://tintruyen.net/9149/13/33.jpg?d=dfgd6546"},{"order":35,"image":"https://tintruyen.net/9149/13/34.jpg?d=dfgd6546"}]},{"order":12,"name":"Chương 12","content":[{"order":1,"image":"https://tintruyen.net/9149/12/0.jpg?d=dfgd6546"},{"order":2,"image":"https://tintruyen.net/9149/12/1.jpg?d=dfgd6546"},{"order":3,"image":"https://tintruyen.net/9149/12/2.jpg?d=dfgd6546"},{"order":4,"image":"https://tintruyen.net/9149/12/3.jpg?d=dfgd6546"},{"order":5,"image":"https://tintruyen.net/9149/12/4.jpg?d=dfgd6546"},{"order":6,"image":"https://tintruyen.net/9149/12/5.jpg?d=dfgd6546"},{"order":7,"image":"https://tintruyen.net/9149/12/6.jpg?d=dfgd6546"},{"order":8,"image":"https://tintruyen.net/9149/12/7.jpg?d=dfgd6546"},{"order":9,"image":"https://tintruyen.net/9149/12/8.jpg?d=dfgd6546"},{"order":10,"image":"https://tintruyen.net/9149/12/9.jpg?d=dfgd6546"},{"order":11,"image":"https://tintruyen.net/9149/12/10.jpg?d=dfgd6546"},{"order":12,"image":"https://tintruyen.net/9149/12/11.jpg?d=dfgd6546"},{"order":13,"image":"https://tintruyen.net/9149/12/12.jpg?d=dfgd6546"},{"order":14,"image":"https://tintruyen.net/9149/12/13.jpg?d=dfgd6546"},{"order":15,"image":"https://tintruyen.net/9149/12/14.jpg?d=dfgd6546"},{"order":16,"image":"https://tintruyen.net/9149/12/15.jpg?d=dfgd6546"},{"order":17,"image":"https://tintruyen.net/9149/12/16.jpg?d=dfgd6546"},{"order":18,"image":"https://tintruyen.net/9149/12/17.jpg?d=dfgd6546"},{"order":19,"image":"https://tintruyen.net/9149/12/18.jpg?d=dfgd6546"},{"order":20,"image":"https://tintruyen.net/9149/12/19.jpg?d=dfgd6546"},{"order":21,"image":"https://tintruyen.net/9149/12/20.jpg?d=dfgd6546"},{"order":22,"image":"https://tintruyen.net/9149/12/21.jpg?d=dfgd6546"},{"order":23,"image":"https://tintruyen.net/9149/12/22.jpg?d=dfgd6546"},{"order":24,"image":"https://tintruyen.net/9149/12/23.jpg?d=dfgd6546"},{"order":25,"image":"https://tintruyen.net/9149/12/24.jpg?d=dfgd6546"},{"order":26,"image":"https://tintruyen.net/9149/12/25.jpg?d=dfgd6546"},{"order":27,"image":"https://tintruyen.net/9149/12/26.jpg?d=dfgd6546"},{"order":28,"image":"https://tintruyen.net/9149/12/27.jpg?d=dfgd6546"},{"order":29,"image":"https://tintruyen.net/9149/12/28.jpg?d=dfgd6546"},{"order":30,"image":"https://tintruyen.net/9149/12/29.jpg?d=dfgd6546"},{"order":31,"image":"https://tintruyen.net/9149/12/30.jpg?d=dfgd6546"},{"order":32,"image":"https://tintruyen.net/9149/12/31.jpg?d=dfgd6546"},{"order":33,"image":"https://tintruyen.net/9149/12/32.jpg?d=dfgd6546"},{"order":34,"image":"https://tintruyen.net/9149/12/33.jpg?d=dfgd6546"}]},{"order":11,"name":"Chương 11","content":[{"order":1,"image":"https://tintruyen.net/9149/11/0.jpg?d=dfgd6546"},{"order":2,"image":"https://tintruyen.net/9149/11/1.jpg?d=dfgd6546"},{"order":3,"image":"https://tintruyen.net/9149/11/2.jpg?d=dfgd6546"},{"order":4,"image":"https://tintruyen.net/9149/11/3.jpg?d=dfgd6546"},{"order":5,"image":"https://tintruyen.net/9149/11/4.jpg?d=dfgd6546"},{"order":6,"image":"https://tintruyen.net/9149/11/5.jpg?d=dfgd6546"},{"order":7,"image":"https://tintruyen.net/9149/11/6.jpg?d=dfgd6546"},{"order":8,"image":"https://tintruyen.net/9149/11/7.jpg?d=dfgd6546"},{"order":9,"image":"https://tintruyen.net/9149/11/8.jpg?d=dfgd6546"},{"order":10,"image":"https://tintruyen.net/9149/11/9.jpg?d=dfgd6546"},{"order":11,"image":"https://tintruyen.net/9149/11/10.jpg?d=dfgd6546"},{"order":12,"image":"https://tintruyen.net/9149/11/11.jpg?d=dfgd6546"},{"order":13,"image":"https://tintruyen.net/9149/11/12.jpg?d=dfgd6546"},{"order":14,"image":"https://tintruyen.net/9149/11/13.jpg?d=dfgd6546"},{"order":15,"image":"https://tintruyen.net/9149/11/14.jpg?d=dfgd6546"},{"order":16,"image":"https://tintruyen.net/9149/11/15.jpg?d=dfgd6546"},{"order":17,"image":"https://tintruyen.net/9149/11/16.jpg?d=dfgd6546"},{"order":18,"image":"https://tintruyen.net/9149/11/17.jpg?d=dfgd6546"},{"order":19,"image":"https://tintruyen.net/9149/11/18.jpg?d=dfgd6546"},{"order":20,"image":"https://tintruyen.net/9149/11/19.jpg?d=dfgd6546"},{"order":21,"image":"https://tintruyen.net/9149/11/20.jpg?d=dfgd6546"},{"order":22,"image":"https://tintruyen.net/9149/11/21.jpg?d=dfgd6546"},{"order":23,"image":"https://tintruyen.net/9149/11/22.jpg?d=dfgd6546"},{"order":24,"image":"https://tintruyen.net/9149/11/23.jpg?d=dfgd6546"},{"order":25,"image":"https://tintruyen.net/9149/11/24.jpg?d=dfgd6546"},{"order":26,"image":"https://tintruyen.net/9149/11/25.jpg?d=dfgd6546"},{"order":27,"image":"https://tintruyen.net/9149/11/26.jpg?d=dfgd6546"},{"order":28,"image":"https://tintruyen.net/9149/11/27.jpg?d=dfgd6546"},{"order":29,"image":"https://tintruyen.net/9149/11/28.jpg?d=dfgd6546"},{"order":30,"image":"https://tintruyen.net/9149/11/29.jpg?d=dfgd6546"},{"order":31,"image":"https://tintruyen.net/9149/11/30.jpg?d=dfgd6546"}]},{"order":10,"name":"Chương 10","content":[{"order":1,"image":"https://tintruyen.net/9149/10/0.jpg?d=dfgd6546"},{"order":2,"image":"https://tintruyen.net/9149/10/1.jpg?d=dfgd6546"},{"order":3,"image":"https://tintruyen.net/9149/10/2.jpg?d=dfgd6546"},{"order":4,"image":"https://tintruyen.net/9149/10/3.jpg?d=dfgd6546"},{"order":5,"image":"https://tintruyen.net/9149/10/4.jpg?d=dfgd6546"},{"order":6,"image":"https://tintruyen.net/9149/10/5.jpg?d=dfgd6546"},{"order":7,"image":"https://tintruyen.net/9149/10/6.jpg?d=dfgd6546"},{"order":8,"image":"https://tintruyen.net/9149/10/7.jpg?d=dfgd6546"},{"order":9,"image":"https://tintruyen.net/9149/10/8.jpg?d=dfgd6546"},{"order":10,"image":"https://tintruyen.net/9149/10/9.jpg?d=dfgd6546"},{"order":11,"image":"https://tintruyen.net/9149/10/10.jpg?d=dfgd6546"},{"order":12,"image":"https://tintruyen.net/9149/10/11.jpg?d=dfgd6546"},{"order":13,"image":"https://tintruyen.net/9149/10/12.jpg?d=dfgd6546"},{"order":14,"image":"https://tintruyen.net/9149/10/13.jpg?d=dfgd6546"},{"order":15,"image":"https://tintruyen.net/9149/10/14.jpg?d=dfgd6546"},{"order":16,"image":"https://tintruyen.net/9149/10/15.jpg?d=dfgd6546"},{"order":17,"image":"https://tintruyen.net/9149/10/16.jpg?d=dfgd6546"},{"order":18,"image":"https://tintruyen.net/9149/10/17.jpg?d=dfgd6546"},{"order":19,"image":"https://tintruyen.net/9149/10/18.jpg?d=dfgd6546"},{"order":20,"image":"https://tintruyen.net/9149/10/19.jpg?d=dfgd6546"},{"order":21,"image":"https://tintruyen.net/9149/10/20.jpg?d=dfgd6546"},{"order":22,"image":"https://tintruyen.net/9149/10/21.jpg?d=dfgd6546"},{"order":23,"image":"https://tintruyen.net/9149/10/22.jpg?d=dfgd6546"},{"order":24,"image":"https://tintruyen.net/9149/10/23.jpg?d=dfgd6546"},{"order":25,"image":"https://tintruyen.net/9149/10/24.jpg?d=dfgd6546"},{"order":26,"image":"https://tintruyen.net/9149/10/25.jpg?d=dfgd6546"},{"order":27,"image":"https://tintruyen.net/9149/10/26.jpg?d=dfgd6546"},{"order":28,"image":"https://tintruyen.net/9149/10/27.jpg?d=dfgd6546"},{"order":29,"image":"https://tintruyen.net/9149/10/28.jpg?d=dfgd6546"},{"order":30,"image":"https://tintruyen.net/9149/10/29.jpg?d=dfgd6546"},{"order":31,"image":"https://tintruyen.net/9149/10/30.jpg?d=dfgd6546"},{"order":32,"image":"https://tintruyen.net/9149/10/31.jpg?d=dfgd6546"},{"order":33,"image":"https://tintruyen.net/9149/10/32.jpg?d=dfgd6546"},{"order":34,"image":"https://tintruyen.net/9149/10/33.jpg?d=dfgd6546"},{"order":35,"image":"https://tintruyen.net/9149/10/34.jpg?d=dfgd6546"},{"order":36,"image":"https://tintruyen.net/9149/10/35.jpg?d=dfgd6546"},{"order":37,"image":"https://tintruyen.net/9149/10/36.jpg?d=dfgd6546"},{"order":38,"image":"https://tintruyen.net/9149/10/37.jpg?d=dfgd6546"}]},{"order":9,"name":"Chương 9","content":[{"order":1,"image":"https://tintruyen.net/9149/9/0.jpg?d=dfgd6546"},{"order":2,"image":"https://tintruyen.net/9149/9/1.jpg?d=dfgd6546"},{"order":3,"image":"https://tintruyen.net/9149/9/2.jpg?d=dfgd6546"},{"order":4,"image":"https://tintruyen.net/9149/9/3.jpg?d=dfgd6546"},{"order":5,"image":"https://tintruyen.net/9149/9/4.jpg?d=dfgd6546"},{"order":6,"image":"https://tintruyen.net/9149/9/5.jpg?d=dfgd6546"},{"order":7,"image":"https://tintruyen.net/9149/9/6.jpg?d=dfgd6546"},{"order":8,"image":"https://tintruyen.net/9149/9/7.jpg?d=dfgd6546"},{"order":9,"image":"https://tintruyen.net/9149/9/8.jpg?d=dfgd6546"},{"order":10,"image":"https://tintruyen.net/9149/9/9.jpg?d=dfgd6546"},{"order":11,"image":"https://tintruyen.net/9149/9/10.jpg?d=dfgd6546"},{"order":12,"image":"https://tintruyen.net/9149/9/11.jpg?d=dfgd6546"},{"order":13,"image":"https://tintruyen.net/9149/9/12.jpg?d=dfgd6546"},{"order":14,"image":"https://tintruyen.net/9149/9/13.jpg?d=dfgd6546"},{"order":15,"image":"https://tintruyen.net/9149/9/14.jpg?d=dfgd6546"},{"order":16,"image":"https://tintruyen.net/9149/9/15.jpg?d=dfgd6546"},{"order":17,"image":"https://tintruyen.net/9149/9/16.jpg?d=dfgd6546"},{"order":18,"image":"https://tintruyen.net/9149/9/17.jpg?d=dfgd6546"},{"order":19,"image":"https://tintruyen.net/9149/9/18.jpg?d=dfgd6546"},{"order":20,"image":"https://tintruyen.net/9149/9/19.jpg?d=dfgd6546"},{"order":21,"image":"https://tintruyen.net/9149/9/20.jpg?d=dfgd6546"},{"order":22,"image":"https://tintruyen.net/9149/9/21.jpg?d=dfgd6546"},{"order":23,"image":"https://tintruyen.net/9149/9/22.jpg?d=dfgd6546"},{"order":24,"image":"https://tintruyen.net/9149/9/23.jpg?d=dfgd6546"},{"order":25,"image":"https://tintruyen.net/9149/9/24.jpg?d=dfgd6546"},{"order":26,"image":"https://tintruyen.net/9149/9/25.jpg?d=dfgd6546"},{"order":27,"image":"https://tintruyen.net/9149/9/26.jpg?d=dfgd6546"},{"order":28,"image":"https://tintruyen.net/9149/9/27.jpg?d=dfgd6546"},{"order":29,"image":"https://tintruyen.net/9149/9/28.jpg?d=dfgd6546"},{"order":30,"image":"https://tintruyen.net/9149/9/29.jpg?d=dfgd6546"},{"order":31,"image":"https://tintruyen.net/9149/9/30.jpg?d=dfgd6546"},{"order":32,"image":"https://tintruyen.net/9149/9/31.jpg?d=dfgd6546"},{"order":33,"image":"https://tintruyen.net/9149/9/32.jpg?d=dfgd6546"}]},{"order":8,"name":"Chương 8","content":[{"order":1,"image":"https://tintruyen.net/9149/8/0.jpg?d=dfgd6546"},{"order":2,"image":"https://tintruyen.net/9149/8/1.jpg?d=dfgd6546"},{"order":3,"image":"https://tintruyen.net/9149/8/2.jpg?d=dfgd6546"},{"order":4,"image":"https://tintruyen.net/9149/8/3.jpg?d=dfgd6546"},{"order":5,"image":"https://tintruyen.net/9149/8/4.jpg?d=dfgd6546"},{"order":6,"image":"https://tintruyen.net/9149/8/5.jpg?d=dfgd6546"},{"order":7,"image":"https://tintruyen.net/9149/8/6.jpg?d=dfgd6546"},{"order":8,"image":"https://tintruyen.net/9149/8/7.jpg?d=dfgd6546"},{"order":9,"image":"https://tintruyen.net/9149/8/8.jpg?d=dfgd6546"},{"order":10,"image":"https://tintruyen.net/9149/8/9.jpg?d=dfgd6546"},{"order":11,"image":"https://tintruyen.net/9149/8/10.jpg?d=dfgd6546"},{"order":12,"image":"https://tintruyen.net/9149/8/11.jpg?d=dfgd6546"},{"order":13,"image":"https://tintruyen.net/9149/8/12.jpg?d=dfgd6546"},{"order":14,"image":"https://tintruyen.net/9149/8/13.jpg?d=dfgd6546"},{"order":15,"image":"https://tintruyen.net/9149/8/14.jpg?d=dfgd6546"},{"order":16,"image":"https://tintruyen.net/9149/8/15.jpg?d=dfgd6546"},{"order":17,"image":"https://tintruyen.net/9149/8/16.jpg?d=dfgd6546"},{"order":18,"image":"https://tintruyen.net/9149/8/17.jpg?d=dfgd6546"},{"order":19,"image":"https://tintruyen.net/9149/8/18.jpg?d=dfgd6546"},{"order":20,"image":"https://tintruyen.net/9149/8/19.jpg?d=dfgd6546"},{"order":21,"image":"https://tintruyen.net/9149/8/20.jpg?d=dfgd6546"},{"order":22,"image":"https://tintruyen.net/9149/8/21.jpg?d=dfgd6546"},{"order":23,"image":"https://tintruyen.net/9149/8/22.jpg?d=dfgd6546"},{"order":24,"image":"https://tintruyen.net/9149/8/23.jpg?d=dfgd6546"},{"order":25,"image":"https://tintruyen.net/9149/8/24.jpg?d=dfgd6546"},{"order":26,"image":"https://tintruyen.net/9149/8/25.jpg?d=dfgd6546"},{"order":27,"image":"https://tintruyen.net/9149/8/26.jpg?d=dfgd6546"},{"order":28,"image":"https://tintruyen.net/9149/8/27.jpg?d=dfgd6546"},{"order":29,"image":"https://tintruyen.net/9149/8/28.jpg?d=dfgd6546"},{"order":30,"image":"https://tintruyen.net/9149/8/29.jpg?d=dfgd6546"},{"order":31,"image":"https://tintruyen.net/9149/8/30.jpg?d=dfgd6546"},{"order":32,"image":"https://tintruyen.net/9149/8/31.jpg?d=dfgd6546"}]},{"order":7,"name":"Chương 7","content":[{"order":1,"image":"https://tintruyen.com/9149/7/0.jpg?tt=3212"},{"order":2,"image":"https://tintruyen.com/9149/7/1.jpg?tt=3212"},{"order":3,"image":"https://tintruyen.com/9149/7/2.jpg?tt=3212"},{"order":4,"image":"https://tintruyen.com/9149/7/3.jpg?tt=3212"},{"order":5,"image":"https://tintruyen.com/9149/7/4.jpg?tt=3212"},{"order":6,"image":"https://tintruyen.com/9149/7/5.jpg?tt=3212"},{"order":7,"image":"https://tintruyen.com/9149/7/6.jpg?tt=3212"},{"order":8,"image":"https://tintruyen.com/9149/7/7.jpg?tt=3212"},{"order":9,"image":"https://tintruyen.com/9149/7/8.jpg?tt=3212"},{"order":10,"image":"https://tintruyen.com/9149/7/9.jpg?tt=3212"},{"order":11,"image":"https://tintruyen.com/9149/7/10.jpg?tt=3212"},{"order":12,"image":"https://tintruyen.com/9149/7/11.jpg?tt=3212"},{"order":13,"image":"https://tintruyen.com/9149/7/12.jpg?tt=3212"},{"order":14,"image":"https://tintruyen.com/9149/7/13.jpg?tt=3212"},{"order":15,"image":"https://tintruyen.com/9149/7/14.jpg?tt=3212"},{"order":16,"image":"https://tintruyen.com/9149/7/15.jpg?tt=3212"},{"order":17,"image":"https://tintruyen.com/9149/7/16.jpg?tt=3212"},{"order":18,"image":"https://tintruyen.com/9149/7/17.jpg?tt=3212"},{"order":19,"image":"https://tintruyen.com/9149/7/18.jpg?tt=3212"},{"order":20,"image":"https://tintruyen.com/9149/7/19.jpg?tt=3212"},{"order":21,"image":"https://tintruyen.com/9149/7/20.jpg?tt=3212"},{"order":22,"image":"https://tintruyen.com/9149/7/21.jpg?tt=3212"},{"order":23,"image":"https://tintruyen.com/9149/7/22.jpg?tt=3212"},{"order":24,"image":"https://tintruyen.com/9149/7/23.jpg?tt=3212"},{"order":25,"image":"https://tintruyen.com/9149/7/24.jpg?tt=3212"},{"order":26,"image":"https://tintruyen.com/9149/7/25.jpg?tt=3212"},{"order":27,"image":"https://tintruyen.com/9149/7/26.jpg?tt=3212"},{"order":28,"image":"https://tintruyen.com/9149/7/27.jpg?tt=3212"}]},{"order":6,"name":"Chương 6","content":[{"order":1,"image":"https://mangaqq.net/9149/fix-6/0.jpg?c=w132321"},{"order":2,"image":"https://mangaqq.net/9149/fix-6/1.jpg?c=w132321"},{"order":3,"image":"https://mangaqq.net/9149/fix-6/2.jpg?c=w132321"},{"order":4,"image":"https://mangaqq.net/9149/fix-6/3.jpg?c=w132321"},{"order":5,"image":"https://mangaqq.net/9149/fix-6/4.jpg?c=w132321"},{"order":6,"image":"https://mangaqq.net/9149/fix-6/5.jpg?c=w132321"},{"order":7,"image":"https://mangaqq.net/9149/fix-6/6.jpg?c=w132321"},{"order":8,"image":"https://mangaqq.net/9149/fix-6/7.jpg?c=w132321"},{"order":9,"image":"https://mangaqq.net/9149/fix-6/8.jpg?c=w132321"},{"order":10,"image":"https://mangaqq.net/9149/fix-6/9.jpg?c=w132321"},{"order":11,"image":"https://mangaqq.net/9149/fix-6/10.jpg?c=w132321"},{"order":12,"image":"https://mangaqq.net/9149/fix-6/11.jpg?c=w132321"},{"order":13,"image":"https://mangaqq.net/9149/fix-6/12.jpg?c=w132321"},{"order":14,"image":"https://mangaqq.net/9149/fix-6/13.jpg?c=w132321"},{"order":15,"image":"https://mangaqq.net/9149/fix-6/14.jpg?c=w132321"},{"order":16,"image":"https://mangaqq.net/9149/fix-6/15.jpg?c=w132321"},{"order":17,"image":"https://mangaqq.net/9149/fix-6/16.jpg?c=w132321"},{"order":18,"image":"https://mangaqq.net/9149/fix-6/17.jpg?c=w132321"},{"order":19,"image":"https://mangaqq.net/9149/fix-6/18.jpg?c=w132321"},{"order":20,"image":"https://mangaqq.net/9149/fix-6/19.jpg?c=w132321"},{"order":21,"image":"https://mangaqq.net/9149/fix-6/20.jpg?c=w132321"},{"order":22,"image":"https://mangaqq.net/9149/fix-6/21.jpg?c=w132321"},{"order":23,"image":"https://mangaqq.net/9149/fix-6/22.jpg?c=w132321"},{"order":24,"image":"https://mangaqq.net/9149/fix-6/23.jpg?c=w132321"},{"order":25,"image":"https://mangaqq.net/9149/fix-6/24.jpg?c=w132321"},{"order":26,"image":"https://mangaqq.net/9149/fix-6/25.jpg?c=w132321"},{"order":27,"image":"https://mangaqq.net/9149/fix-6/26.jpg?c=w132321"},{"order":28,"image":"https://mangaqq.net/9149/fix-6/27.jpg?c=w132321"},{"order":29,"image":"https://mangaqq.net/9149/fix-6/28.jpg?c=w132321"}]},{"order":5,"name":"Chương 5","content":[{"order":1,"image":"https://mangaqq.net/9149/5/0.jpg?c=w132321"},{"order":2,"image":"https://mangaqq.net/9149/5/1.jpg?c=w132321"},{"order":3,"image":"https://mangaqq.net/9149/5/2.jpg?c=w132321"},{"order":4,"image":"https://mangaqq.net/9149/5/3.jpg?c=w132321"},{"order":5,"image":"https://mangaqq.net/9149/5/4.jpg?c=w132321"},{"order":6,"image":"https://mangaqq.net/9149/5/5.jpg?c=w132321"},{"order":7,"image":"https://mangaqq.net/9149/5/6.jpg?c=w132321"},{"order":8,"image":"https://mangaqq.net/9149/5/7.jpg?c=w132321"},{"order":9,"image":"https://mangaqq.net/9149/5/8.jpg?c=w132321"},{"order":10,"image":"https://mangaqq.net/9149/5/9.jpg?c=w132321"},{"order":11,"image":"https://mangaqq.net/9149/5/10.jpg?c=w132321"},{"order":12,"image":"https://mangaqq.net/9149/5/11.jpg?c=w132321"},{"order":13,"image":"https://mangaqq.net/9149/5/12.jpg?c=w132321"},{"order":14,"image":"https://mangaqq.net/9149/5/13.jpg?c=w132321"},{"order":15,"image":"https://mangaqq.net/9149/5/14.jpg?c=w132321"},{"order":16,"image":"https://mangaqq.net/9149/5/15.jpg?c=w132321"},{"order":17,"image":"https://mangaqq.net/9149/5/16.jpg?c=w132321"},{"order":18,"image":"https://mangaqq.net/9149/5/17.jpg?c=w132321"},{"order":19,"image":"https://mangaqq.net/9149/5/18.jpg?c=w132321"},{"order":20,"image":"https://mangaqq.net/9149/5/19.jpg?c=w132321"},{"order":21,"image":"https://mangaqq.net/9149/5/20.jpg?c=w132321"},{"order":22,"image":"https://mangaqq.net/9149/5/21.jpg?c=w132321"},{"order":23,"image":"https://mangaqq.net/9149/5/22.jpg?c=w132321"},{"order":24,"image":"https://mangaqq.net/9149/5/23.jpg?c=w132321"},{"order":25,"image":"https://mangaqq.net/9149/5/24.jpg?c=w132321"},{"order":26,"image":"https://mangaqq.net/9149/5/25.jpg?c=w132321"},{"order":27,"image":"https://mangaqq.net/9149/5/26.jpg?c=w132321"},{"order":28,"image":"https://mangaqq.net/9149/5/27.jpg?c=w132321"},{"order":29,"image":"https://mangaqq.net/9149/5/28.jpg?c=w132321"},{"order":30,"image":"https://mangaqq.net/9149/5/29.jpg?c=w132321"},{"order":31,"image":"https://mangaqq.net/9149/5/30.jpg?c=w132321"},{"order":32,"image":"https://mangaqq.net/9149/5/31.jpg?c=w132321"},{"order":33,"image":"https://mangaqq.net/9149/5/33.jpg?c=w132321"}]},{"order":4,"name":"Chương 4","content":[{"order":1,"image":"https://mangaqq.net/9149/4/0.jpg?c=w132321"},{"order":2,"image":"https://mangaqq.net/9149/4/1.jpg?c=w132321"},{"order":3,"image":"https://mangaqq.net/9149/4/2.jpg?c=w132321"},{"order":4,"image":"https://mangaqq.net/9149/4/3.jpg?c=w132321"},{"order":5,"image":"https://mangaqq.net/9149/4/4.jpg?c=w132321"},{"order":6,"image":"https://mangaqq.net/9149/4/5.jpg?c=w132321"},{"order":7,"image":"https://mangaqq.net/9149/4/6.jpg?c=w132321"},{"order":8,"image":"https://mangaqq.net/9149/4/7.jpg?c=w132321"},{"order":9,"image":"https://mangaqq.net/9149/4/8.jpg?c=w132321"},{"order":10,"image":"https://mangaqq.net/9149/4/9.jpg?c=w132321"},{"order":11,"image":"https://mangaqq.net/9149/4/10.jpg?c=w132321"},{"order":12,"image":"https://mangaqq.net/9149/4/11.jpg?c=w132321"},{"order":13,"image":"https://mangaqq.net/9149/4/12.jpg?c=w132321"},{"order":14,"image":"https://mangaqq.net/9149/4/13.jpg?c=w132321"},{"order":15,"image":"https://mangaqq.net/9149/4/14.jpg?c=w132321"},{"order":16,"image":"https://mangaqq.net/9149/4/15.jpg?c=w132321"},{"order":17,"image":"https://mangaqq.net/9149/4/16.jpg?c=w132321"},{"order":18,"image":"https://mangaqq.net/9149/4/17.jpg?c=w132321"},{"order":19,"image":"https://mangaqq.net/9149/4/18.jpg?c=w132321"},{"order":20,"image":"https://mangaqq.net/9149/4/19.jpg?c=w132321"},{"order":21,"image":"https://mangaqq.net/9149/4/20.jpg?c=w132321"},{"order":22,"image":"https://mangaqq.net/9149/4/21.jpg?c=w132321"},{"order":23,"image":"https://mangaqq.net/9149/4/22.jpg?c=w132321"},{"order":24,"image":"https://mangaqq.net/9149/4/23.jpg?c=w132321"},{"order":25,"image":"https://mangaqq.net/9149/4/24.jpg?c=w132321"},{"order":26,"image":"https://mangaqq.net/9149/4/25.jpg?c=w132321"},{"order":27,"image":"https://mangaqq.net/9149/4/26.jpg?c=w132321"},{"order":28,"image":"https://mangaqq.net/9149/4/27.jpg?c=w132321"}]},{"order":3,"name":"Chương 3","content":[{"order":1,"image":"https://mangaqq.net/9149/3/0.jpg?c=w132321"},{"order":2,"image":"https://mangaqq.net/9149/3/1.jpg?c=w132321"},{"order":3,"image":"https://mangaqq.net/9149/3/2.jpg?c=w132321"},{"order":4,"image":"https://mangaqq.net/9149/3/3.jpg?c=w132321"},{"order":5,"image":"https://mangaqq.net/9149/3/4.jpg?c=w132321"},{"order":6,"image":"https://mangaqq.net/9149/3/5.jpg?c=w132321"},{"order":7,"image":"https://mangaqq.net/9149/3/6.jpg?c=w132321"},{"order":8,"image":"https://mangaqq.net/9149/3/7.jpg?c=w132321"},{"order":9,"image":"https://mangaqq.net/9149/3/8.jpg?c=w132321"},{"order":10,"image":"https://mangaqq.net/9149/3/9.jpg?c=w132321"},{"order":11,"image":"https://mangaqq.net/9149/3/10.jpg?c=w132321"},{"order":12,"image":"https://mangaqq.net/9149/3/11.jpg?c=w132321"},{"order":13,"image":"https://mangaqq.net/9149/3/12.jpg?c=w132321"},{"order":14,"image":"https://mangaqq.net/9149/3/13.jpg?c=w132321"},{"order":15,"image":"https://mangaqq.net/9149/3/14.jpg?c=w132321"},{"order":16,"image":"https://mangaqq.net/9149/3/15.jpg?c=w132321"},{"order":17,"image":"https://mangaqq.net/9149/3/16.jpg?c=w132321"},{"order":18,"image":"https://mangaqq.net/9149/3/17.jpg?c=w132321"},{"order":19,"image":"https://mangaqq.net/9149/3/18.jpg?c=w132321"},{"order":20,"image":"https://mangaqq.net/9149/3/19.jpg?c=w132321"},{"order":21,"image":"https://mangaqq.net/9149/3/20.jpg?c=w132321"},{"order":22,"image":"https://mangaqq.net/9149/3/21.jpg?c=w132321"},{"order":23,"image":"https://mangaqq.net/9149/3/22.jpg?c=w132321"},{"order":24,"image":"https://mangaqq.net/9149/3/23.jpg?c=w132321"},{"order":25,"image":"https://mangaqq.net/9149/3/24.jpg?c=w132321"}]},{"order":2,"name":"Chương 2","content":[{"order":1,"image":"https://mangaqq.net/9149/2/0.jpg?c=w132321"},{"order":2,"image":"https://mangaqq.net/9149/2/1.jpg?c=w132321"},{"order":3,"image":"https://mangaqq.net/9149/2/2.jpg?c=w132321"},{"order":4,"image":"https://mangaqq.net/9149/2/3.jpg?c=w132321"},{"order":5,"image":"https://mangaqq.net/9149/2/4.jpg?c=w132321"},{"order":6,"image":"https://mangaqq.net/9149/2/5.jpg?c=w132321"},{"order":7,"image":"https://mangaqq.net/9149/2/6.jpg?c=w132321"},{"order":8,"image":"https://mangaqq.net/9149/2/7.jpg?c=w132321"},{"order":9,"image":"https://mangaqq.net/9149/2/8.jpg?c=w132321"},{"order":10,"image":"https://mangaqq.net/9149/2/9.jpg?c=w132321"},{"order":11,"image":"https://mangaqq.net/9149/2/10.jpg?c=w132321"},{"order":12,"image":"https://mangaqq.net/9149/2/11.jpg?c=w132321"},{"order":13,"image":"https://mangaqq.net/9149/2/12.jpg?c=w132321"},{"order":14,"image":"https://mangaqq.net/9149/2/13.jpg?c=w132321"},{"order":15,"image":"https://mangaqq.net/9149/2/14.jpg?c=w132321"},{"order":16,"image":"https://mangaqq.net/9149/2/15.jpg?c=w132321"},{"order":17,"image":"https://mangaqq.net/9149/2/16.jpg?c=w132321"},{"order":18,"image":"https://mangaqq.net/9149/2/17.jpg?c=w132321"},{"order":19,"image":"https://mangaqq.net/9149/2/18.jpg?c=w132321"},{"order":20,"image":"https://mangaqq.net/9149/2/19.jpg?c=w132321"},{"order":21,"image":"https://mangaqq.net/9149/2/20.jpg?c=w132321"},{"order":22,"image":"https://mangaqq.net/9149/2/21.jpg?c=w132321"},{"order":23,"image":"https://mangaqq.net/9149/2/22.jpg?c=w132321"},{"order":24,"image":"https://mangaqq.net/9149/2/23.jpg?c=w132321"},{"order":25,"image":"https://mangaqq.net/9149/2/24.jpg?c=w132321"},{"order":26,"image":"https://mangaqq.net/9149/2/25.jpg?c=w132321"},{"order":27,"image":"https://mangaqq.net/9149/2/26.jpg?c=w132321"},{"order":28,"image":"https://mangaqq.net/9149/2/27.jpg?c=w132321"},{"order":29,"image":"https://mangaqq.net/9149/2/28.jpg?c=w132321"},{"order":30,"image":"https://mangaqq.net/9149/2/29.jpg?c=w132321"},{"order":31,"image":"https://mangaqq.net/9149/2/30.jpg?c=w132321"}]},{"order":1,"name":"Chương 1","content":[{"order":1,"image":"https://mangaqq.net/9149/1/0.jpg?c=w132321"},{"order":2,"image":"https://mangaqq.net/9149/1/1.jpg?c=w132321"},{"order":3,"image":"https://mangaqq.net/9149/1/2.jpg?c=w132321"},{"order":4,"image":"https://mangaqq.net/9149/1/3.jpg?c=w132321"},{"order":5,"image":"https://mangaqq.net/9149/1/4.jpg?c=w132321"},{"order":6,"image":"https://mangaqq.net/9149/1/5.jpg?c=w132321"},{"order":7,"image":"https://mangaqq.net/9149/1/6.jpg?c=w132321"},{"order":8,"image":"https://mangaqq.net/9149/1/7.jpg?c=w132321"},{"order":9,"image":"https://mangaqq.net/9149/1/8.jpg?c=w132321"},{"order":10,"image":"https://mangaqq.net/9149/1/9.jpg?c=w132321"},{"order":11,"image":"https://mangaqq.net/9149/1/10.jpg?c=w132321"},{"order":12,"image":"https://mangaqq.net/9149/1/11.jpg?c=w132321"},{"order":13,"image":"https://mangaqq.net/9149/1/12.jpg?c=w132321"},{"order":14,"image":"https://mangaqq.net/9149/1/13.jpg?c=w132321"},{"order":15,"image":"https://mangaqq.net/9149/1/14.jpg?c=w132321"},{"order":16,"image":"https://mangaqq.net/9149/1/15.jpg?c=w132321"},{"order":17,"image":"https://mangaqq.net/9149/1/16.jpg?c=w132321"},{"order":18,"image":"https://mangaqq.net/9149/1/17.jpg?c=w132321"},{"order":19,"image":"https://mangaqq.net/9149/1/18.jpg?c=w132321"},{"order":20,"image":"https://mangaqq.net/9149/1/19.jpg?c=w132321"},{"order":21,"image":"https://mangaqq.net/9149/1/20.jpg?c=w132321"},{"order":22,"image":"https://mangaqq.net/9149/1/21.jpg?c=w132321"},{"order":23,"image":"https://mangaqq.net/9149/1/22.jpg?c=w132321"},{"order":24,"image":"https://mangaqq.net/9149/1/23.jpg?c=w132321"},{"order":25,"image":"https://mangaqq.net/9149/1/24.jpg?c=w132321"},{"order":26,"image":"https://mangaqq.net/9149/1/25.jpg?c=w132321"},{"order":27,"image":"https://mangaqq.net/9149/1/26.jpg?c=w132321"},{"order":28,"image":"https://mangaqq.net/9149/1/27.jpg?c=w132321"},{"order":29,"image":"https://mangaqq.net/9149/1/28.jpg?c=w132321"},{"order":30,"image":"https://mangaqq.net/9149/1/29.jpg?c=w132321"},{"order":31,"image":"https://mangaqq.net/9149/1/30.jpg?c=w132321"},{"order":32,"image":"https://mangaqq.net/9149/1/31.jpg?c=w132321"},{"order":33,"image":"https://mangaqq.net/9149/1/32.jpg?c=w132321"},{"order":34,"image":"https://mangaqq.net/9149/1/33.jpg?c=w132321"},{"order":35,"image":"https://mangaqq.net/9149/1/34.jpg?c=w132321"},{"order":36,"image":"https://mangaqq.net/9149/1/35.jpg?c=w132321"},{"order":37,"image":"https://mangaqq.net/9149/1/36.jpg?c=w132321"},{"order":38,"image":"https://mangaqq.net/9149/1/37.jpg?c=w132321"},{"order":39,"image":"https://mangaqq.net/9149/1/38.jpg?c=w132321"},{"order":40,"image":"https://mangaqq.net/9149/1/39.jpg?c=w132321"},{"order":41,"image":"https://mangaqq.net/9149/1/40.jpg?c=w132321"},{"order":42,"image":"https://mangaqq.net/9149/1/41.jpg?c=w132321"},{"order":43,"image":"https://mangaqq.net/9149/1/42.jpg?c=w132321"},{"order":44,"image":"https://mangaqq.net/9149/1/43.jpg?c=w132321"},{"order":45,"image":"https://mangaqq.net/9149/1/44.jpg?c=w132321"},{"order":46,"image":"https://mangaqq.net/9149/1/45.jpg?c=w132321"}]}]}