{"title":"Dị Giới Thất Cách","coverImageUrl":"https://i.truyenvua.com/ebook/190x247/di-gioi-that-cach_1654322613.jpg?gt=hdfgdfg&mobile=2","description":"Một thanh niên đi tìm người yêu ở dị giới để rủ ẻm tự sát cùng mình.","link":"https://truyenqqviet.com/truyen-tranh/di-gioi-that-cach-12390","chapters":[{"order":27,"name":"Chương 26","content":[{"order":1,"image":"https://truyenvua.com/12390/fix-26/0.jpg?gt=hdfgdfg"},{"order":2,"image":"https://truyenvua.com/12390/fix-26/1.jpg?gt=hdfgdfg"},{"order":3,"image":"https://truyenvua.com/12390/fix-26/2.jpg?gt=hdfgdfg"},{"order":4,"image":"https://truyenvua.com/12390/fix-26/3.jpg?gt=hdfgdfg"},{"order":5,"image":"https://truyenvua.com/12390/fix-26/4.jpg?gt=hdfgdfg"},{"order":6,"image":"https://truyenvua.com/12390/fix-26/5.jpg?gt=hdfgdfg"},{"order":7,"image":"https://truyenvua.com/12390/fix-26/6.jpg?gt=hdfgdfg"},{"order":8,"image":"https://truyenvua.com/12390/fix-26/7.jpg?gt=hdfgdfg"},{"order":9,"image":"https://truyenvua.com/12390/fix-26/8.jpg?gt=hdfgdfg"},{"order":10,"image":"https://truyenvua.com/12390/fix-26/9.jpg?gt=hdfgdfg"},{"order":11,"image":"https://truyenvua.com/12390/fix-26/10.jpg?gt=hdfgdfg"},{"order":12,"image":"https://truyenvua.com/12390/fix-26/11.jpg?gt=hdfgdfg"},{"order":13,"image":"https://truyenvua.com/12390/fix-26/12.jpg?gt=hdfgdfg"},{"order":14,"image":"https://truyenvua.com/12390/fix-26/13.jpg?gt=hdfgdfg"},{"order":15,"image":"https://truyenvua.com/12390/fix-26/14.jpg?gt=hdfgdfg"},{"order":16,"image":"https://truyenvua.com/12390/fix-26/15.jpg?gt=hdfgdfg"},{"order":17,"image":"https://truyenvua.com/12390/fix-26/16.jpg?gt=hdfgdfg"},{"order":18,"image":"https://truyenvua.com/12390/fix-26/17.jpg?gt=hdfgdfg"},{"order":19,"image":"https://truyenvua.com/12390/fix-26/18.jpg?gt=hdfgdfg"},{"order":20,"image":"https://truyenvua.com/12390/fix-26/19.jpg?gt=hdfgdfg"},{"order":21,"image":"https://truyenvua.com/12390/fix-26/20.jpg?gt=hdfgdfg"},{"order":22,"image":"https://truyenvua.com/12390/fix-26/21.jpg?gt=hdfgdfg"},{"order":23,"image":"https://truyenvua.com/12390/fix-26/22.jpg?gt=hdfgdfg"},{"order":24,"image":"https://truyenvua.com/12390/fix-26/23.jpg?gt=hdfgdfg"},{"order":25,"image":"https://truyenvua.com/12390/fix-26/24.jpg?gt=hdfgdfg"},{"order":26,"image":"https://truyenvua.com/12390/fix-26/25.jpg?gt=hdfgdfg"},{"order":27,"image":"https://truyenvua.com/12390/fix-26/26.jpg?gt=hdfgdfg"},{"order":28,"image":"https://truyenvua.com/12390/fix-26/27.jpg?gt=hdfgdfg"}]},{"order":26,"name":"Chương 25","content":[{"order":1,"image":"https://truyenvua.com/12390/25/0_ccnt6.jpg?gt=hdfgdfg"},{"order":2,"image":"https://truyenvua.com/12390/25/1_cumo9.jpg?gt=hdfgdfg"},{"order":3,"image":"https://truyenvua.com/12390/25/2_jxbil.jpg?gt=hdfgdfg"},{"order":4,"image":"https://truyenvua.com/12390/25/3_gg2ul.jpg?gt=hdfgdfg"},{"order":5,"image":"https://truyenvua.com/12390/25/4_7bd0b.jpg?gt=hdfgdfg"},{"order":6,"image":"https://truyenvua.com/12390/25/5_mxvo1.jpg?gt=hdfgdfg"},{"order":7,"image":"https://truyenvua.com/12390/25/6_n0r6f.jpg?gt=hdfgdfg"},{"order":8,"image":"https://truyenvua.com/12390/25/7_alaky.jpg?gt=hdfgdfg"},{"order":9,"image":"https://truyenvua.com/12390/25/8_8vx9p.jpg?gt=hdfgdfg"},{"order":10,"image":"https://truyenvua.com/12390/25/9_2rn0o.jpg?gt=hdfgdfg"},{"order":11,"image":"https://truyenvua.com/12390/25/10_ce9z8.jpg?gt=hdfgdfg"},{"order":12,"image":"https://truyenvua.com/12390/25/11_xktqt.jpg?gt=hdfgdfg"},{"order":13,"image":"https://truyenvua.com/12390/25/12_14t6p.jpg?gt=hdfgdfg"},{"order":14,"image":"https://truyenvua.com/12390/25/13_bjnuv.jpg?gt=hdfgdfg"},{"order":15,"image":"https://truyenvua.com/12390/25/14_yeg1r.jpg?gt=hdfgdfg"},{"order":16,"image":"https://truyenvua.com/12390/25/15_mrkj3.jpg?gt=hdfgdfg"},{"order":17,"image":"https://truyenvua.com/12390/25/16_t1zsf.jpg?gt=hdfgdfg"},{"order":18,"image":"https://truyenvua.com/12390/25/17_ib2i6.jpg?gt=hdfgdfg"},{"order":19,"image":"https://truyenvua.com/12390/25/18_b3suj.jpg?gt=hdfgdfg"},{"order":20,"image":"https://truyenvua.com/12390/25/19_1gu4p.jpg?gt=hdfgdfg"},{"order":21,"image":"https://truyenvua.com/12390/25/20_1ov8a.jpg?gt=hdfgdfg"},{"order":22,"image":"https://truyenvua.com/12390/25/21_nhzcu.jpg?gt=hdfgdfg"}]},{"order":25,"name":"Chương 24","content":[{"order":1,"image":"https://hinhhinh.com/12390/fix-24/0.jpg?gt=hdfgdfg"},{"order":2,"image":"https://hinhhinh.com/12390/fix-24/1.jpg?gt=hdfgdfg"},{"order":3,"image":"https://hinhhinh.com/12390/fix-24/2.jpg?gt=hdfgdfg"},{"order":4,"image":"https://hinhhinh.com/12390/fix-24/3.jpg?gt=hdfgdfg"},{"order":5,"image":"https://hinhhinh.com/12390/fix-24/4.jpg?gt=hdfgdfg"},{"order":6,"image":"https://hinhhinh.com/12390/fix-24/5.jpg?gt=hdfgdfg"},{"order":7,"image":"https://hinhhinh.com/12390/fix-24/6.jpg?gt=hdfgdfg"},{"order":8,"image":"https://hinhhinh.com/12390/fix-24/7.jpg?gt=hdfgdfg"},{"order":9,"image":"https://hinhhinh.com/12390/fix-24/8.jpg?gt=hdfgdfg"},{"order":10,"image":"https://hinhhinh.com/12390/fix-24/9.jpg?gt=hdfgdfg"},{"order":11,"image":"https://hinhhinh.com/12390/fix-24/10.jpg?gt=hdfgdfg"},{"order":12,"image":"https://hinhhinh.com/12390/fix-24/11.jpg?gt=hdfgdfg"},{"order":13,"image":"https://hinhhinh.com/12390/fix-24/12.jpg?gt=hdfgdfg"},{"order":14,"image":"https://hinhhinh.com/12390/fix-24/13.jpg?gt=hdfgdfg"},{"order":15,"image":"https://hinhhinh.com/12390/fix-24/14.jpg?gt=hdfgdfg"},{"order":16,"image":"https://hinhhinh.com/12390/fix-24/15.jpg?gt=hdfgdfg"},{"order":17,"image":"https://hinhhinh.com/12390/fix-24/16.jpg?gt=hdfgdfg"},{"order":18,"image":"https://hinhhinh.com/12390/fix-24/17.jpg?gt=hdfgdfg"},{"order":19,"image":"https://hinhhinh.com/12390/fix-24/18.jpg?gt=hdfgdfg"},{"order":20,"image":"https://hinhhinh.com/12390/fix-24/19.jpg?gt=hdfgdfg"},{"order":21,"image":"https://hinhhinh.com/12390/fix-24/20.jpg?gt=hdfgdfg"},{"order":22,"image":"https://hinhhinh.com/12390/fix-24/21.jpg?gt=hdfgdfg"},{"order":23,"image":"https://hinhhinh.com/12390/fix-24/22.jpg?gt=hdfgdfg"},{"order":24,"image":"https://hinhhinh.com/12390/fix-24/23.jpg?gt=hdfgdfg"},{"order":25,"image":"https://hinhhinh.com/12390/fix-24/24.jpg?gt=hdfgdfg"},{"order":26,"image":"https://hinhhinh.com/12390/fix-24/25.jpg?gt=hdfgdfg"},{"order":27,"image":"https://hinhhinh.com/12390/fix-24/26.jpg?gt=hdfgdfg"},{"order":28,"image":"https://hinhhinh.com/12390/fix-24/27.jpg?gt=hdfgdfg"},{"order":29,"image":"https://hinhhinh.com/12390/fix-24/28.jpg?gt=hdfgdfg"},{"order":30,"image":"https://hinhhinh.com/12390/fix-24/29.jpg?gt=hdfgdfg"},{"order":31,"image":"https://hinhhinh.com/12390/fix-24/30.jpg?gt=hdfgdfg"},{"order":32,"image":"https://hinhhinh.com/12390/fix-24/31.jpg?gt=hdfgdfg"}]},{"order":24,"name":"Chương 23","content":[{"order":1,"image":"https://hinhhinh.com/12390/23/0.jpg?gt=hdfgdfg"},{"order":2,"image":"https://hinhhinh.com/12390/23/1.jpg?gt=hdfgdfg"},{"order":3,"image":"https://hinhhinh.com/12390/23/2.jpg?gt=hdfgdfg"},{"order":4,"image":"https://hinhhinh.com/12390/23/3.jpg?gt=hdfgdfg"},{"order":5,"image":"https://hinhhinh.com/12390/23/4.jpg?gt=hdfgdfg"},{"order":6,"image":"https://hinhhinh.com/12390/23/5.jpg?gt=hdfgdfg"},{"order":7,"image":"https://hinhhinh.com/12390/23/6.jpg?gt=hdfgdfg"},{"order":8,"image":"https://hinhhinh.com/12390/23/7.jpg?gt=hdfgdfg"},{"order":9,"image":"https://hinhhinh.com/12390/23/8.jpg?gt=hdfgdfg"},{"order":10,"image":"https://hinhhinh.com/12390/23/9.jpg?gt=hdfgdfg"},{"order":11,"image":"https://hinhhinh.com/12390/23/10.jpg?gt=hdfgdfg"},{"order":12,"image":"https://hinhhinh.com/12390/23/11.jpg?gt=hdfgdfg"},{"order":13,"image":"https://hinhhinh.com/12390/23/12.jpg?gt=hdfgdfg"},{"order":14,"image":"https://hinhhinh.com/12390/23/13.jpg?gt=hdfgdfg"},{"order":15,"image":"https://hinhhinh.com/12390/23/14.jpg?gt=hdfgdfg"},{"order":16,"image":"https://hinhhinh.com/12390/23/15.jpg?gt=hdfgdfg"},{"order":17,"image":"https://hinhhinh.com/12390/23/16.jpg?gt=hdfgdfg"},{"order":18,"image":"https://hinhhinh.com/12390/23/17.jpg?gt=hdfgdfg"},{"order":19,"image":"https://hinhhinh.com/12390/23/18.jpg?gt=hdfgdfg"},{"order":20,"image":"https://hinhhinh.com/12390/23/19.jpg?gt=hdfgdfg"},{"order":21,"image":"https://hinhhinh.com/12390/23/20.jpg?gt=hdfgdfg"},{"order":22,"image":"https://hinhhinh.com/12390/23/21.jpg?gt=hdfgdfg"},{"order":23,"image":"https://hinhhinh.com/12390/23/22.jpg?gt=hdfgdfg"},{"order":24,"image":"https://hinhhinh.com/12390/23/23.jpg?gt=hdfgdfg"},{"order":25,"image":"https://hinhhinh.com/12390/23/24.jpg?gt=hdfgdfg"},{"order":26,"image":"https://hinhhinh.com/12390/23/25.jpg?gt=hdfgdfg"},{"order":27,"image":"https://hinhhinh.com/12390/23/26.jpg?gt=hdfgdfg"}]},{"order":23,"name":"Chương 22","content":[{"order":1,"image":"https://hinhhinh.com/12390/fix-22/0.jpg?gt=hdfgdfg"},{"order":2,"image":"https://hinhhinh.com/12390/fix-22/1.jpg?gt=hdfgdfg"},{"order":3,"image":"https://hinhhinh.com/12390/fix-22/2.jpg?gt=hdfgdfg"},{"order":4,"image":"https://hinhhinh.com/12390/fix-22/3.jpg?gt=hdfgdfg"},{"order":5,"image":"https://hinhhinh.com/12390/fix-22/4.jpg?gt=hdfgdfg"},{"order":6,"image":"https://hinhhinh.com/12390/fix-22/5.jpg?gt=hdfgdfg"},{"order":7,"image":"https://hinhhinh.com/12390/fix-22/6.jpg?gt=hdfgdfg"},{"order":8,"image":"https://hinhhinh.com/12390/fix-22/7.jpg?gt=hdfgdfg"},{"order":9,"image":"https://hinhhinh.com/12390/fix-22/8.jpg?gt=hdfgdfg"},{"order":10,"image":"https://hinhhinh.com/12390/fix-22/9.jpg?gt=hdfgdfg"},{"order":11,"image":"https://hinhhinh.com/12390/fix-22/10.jpg?gt=hdfgdfg"},{"order":12,"image":"https://hinhhinh.com/12390/fix-22/11.jpg?gt=hdfgdfg"},{"order":13,"image":"https://hinhhinh.com/12390/fix-22/12.jpg?gt=hdfgdfg"},{"order":14,"image":"https://hinhhinh.com/12390/fix-22/13.jpg?gt=hdfgdfg"},{"order":15,"image":"https://hinhhinh.com/12390/fix-22/14.jpg?gt=hdfgdfg"},{"order":16,"image":"https://hinhhinh.com/12390/fix-22/15.jpg?gt=hdfgdfg"},{"order":17,"image":"https://hinhhinh.com/12390/fix-22/16.jpg?gt=hdfgdfg"},{"order":18,"image":"https://hinhhinh.com/12390/fix-22/17.jpg?gt=hdfgdfg"},{"order":19,"image":"https://hinhhinh.com/12390/fix-22/18.jpg?gt=hdfgdfg"},{"order":20,"image":"https://hinhhinh.com/12390/fix-22/19.jpg?gt=hdfgdfg"},{"order":21,"image":"https://hinhhinh.com/12390/fix-22/20.jpg?gt=hdfgdfg"},{"order":22,"image":"https://hinhhinh.com/12390/fix-22/21.jpg?gt=hdfgdfg"},{"order":23,"image":"https://hinhhinh.com/12390/fix-22/22.jpg?gt=hdfgdfg"},{"order":24,"image":"https://hinhhinh.com/12390/fix-22/23.jpg?gt=hdfgdfg"},{"order":25,"image":"https://hinhhinh.com/12390/fix-22/24.jpg?gt=hdfgdfg"},{"order":26,"image":"https://hinhhinh.com/12390/fix-22/25.jpg?gt=hdfgdfg"},{"order":27,"image":"https://hinhhinh.com/12390/fix-22/26.jpg?gt=hdfgdfg"},{"order":28,"image":"https://hinhhinh.com/12390/fix-22/27.jpg?gt=hdfgdfg"},{"order":29,"image":"https://hinhhinh.com/12390/fix-22/28.jpg?gt=hdfgdfg"},{"order":30,"image":"https://hinhhinh.com/12390/fix-22/29.jpg?gt=hdfgdfg"},{"order":31,"image":"https://hinhhinh.com/12390/fix-22/30.jpg?gt=hdfgdfg"},{"order":32,"image":"https://hinhhinh.com/12390/fix-22/31.jpg?gt=hdfgdfg"}]},{"order":22,"name":"Chương 21","content":[{"order":1,"image":"https://hinhhinh.com/12390/fix-21/0.jpg?gt=hdfgdfg"},{"order":2,"image":"https://hinhhinh.com/12390/fix-21/1.jpg?gt=hdfgdfg"},{"order":3,"image":"https://hinhhinh.com/12390/fix-21/2.jpg?gt=hdfgdfg"},{"order":4,"image":"https://hinhhinh.com/12390/fix-21/3.jpg?gt=hdfgdfg"},{"order":5,"image":"https://hinhhinh.com/12390/fix-21/4.jpg?gt=hdfgdfg"},{"order":6,"image":"https://hinhhinh.com/12390/fix-21/5.jpg?gt=hdfgdfg"},{"order":7,"image":"https://hinhhinh.com/12390/fix-21/6.jpg?gt=hdfgdfg"},{"order":8,"image":"https://hinhhinh.com/12390/fix-21/7.jpg?gt=hdfgdfg"},{"order":9,"image":"https://hinhhinh.com/12390/fix-21/8.jpg?gt=hdfgdfg"},{"order":10,"image":"https://hinhhinh.com/12390/fix-21/9.jpg?gt=hdfgdfg"},{"order":11,"image":"https://hinhhinh.com/12390/fix-21/10.jpg?gt=hdfgdfg"},{"order":12,"image":"https://hinhhinh.com/12390/fix-21/11.jpg?gt=hdfgdfg"},{"order":13,"image":"https://hinhhinh.com/12390/fix-21/12.jpg?gt=hdfgdfg"},{"order":14,"image":"https://hinhhinh.com/12390/fix-21/13.jpg?gt=hdfgdfg"},{"order":15,"image":"https://hinhhinh.com/12390/fix-21/14.jpg?gt=hdfgdfg"},{"order":16,"image":"https://hinhhinh.com/12390/fix-21/15.jpg?gt=hdfgdfg"},{"order":17,"image":"https://hinhhinh.com/12390/fix-21/16.jpg?gt=hdfgdfg"},{"order":18,"image":"https://hinhhinh.com/12390/fix-21/17.jpg?gt=hdfgdfg"},{"order":19,"image":"https://hinhhinh.com/12390/fix-21/18.jpg?gt=hdfgdfg"},{"order":20,"image":"https://hinhhinh.com/12390/fix-21/19.jpg?gt=hdfgdfg"},{"order":21,"image":"https://hinhhinh.com/12390/fix-21/20.jpg?gt=hdfgdfg"},{"order":22,"image":"https://hinhhinh.com/12390/fix-21/21.jpg?gt=hdfgdfg"},{"order":23,"image":"https://hinhhinh.com/12390/fix-21/22.jpg?gt=hdfgdfg"},{"order":24,"image":"https://hinhhinh.com/12390/fix-21/23.jpg?gt=hdfgdfg"},{"order":25,"image":"https://hinhhinh.com/12390/fix-21/24.jpg?gt=hdfgdfg"},{"order":26,"image":"https://hinhhinh.com/12390/fix-21/25.jpg?gt=hdfgdfg"},{"order":27,"image":"https://hinhhinh.com/12390/fix-21/26.jpg?gt=hdfgdfg"},{"order":28,"image":"https://hinhhinh.com/12390/fix-21/27.jpg?gt=hdfgdfg"}]},{"order":21,"name":"Chương 20.1","content":[{"order":1,"image":"https://hinhhinh.com/12390/20.1/0.jpg?gt=hdfgdfg"},{"order":2,"image":"https://hinhhinh.com/12390/20.1/1.jpg?gt=hdfgdfg"}]},{"order":20,"name":"Chương 20","content":[{"order":1,"image":"https://tintruyen.net/12390/fix-20/0.jpg?d=dfgd6546"},{"order":2,"image":"https://tintruyen.net/12390/fix-20/1.jpg?d=dfgd6546"},{"order":3,"image":"https://tintruyen.net/12390/fix-20/2.jpg?d=dfgd6546"},{"order":4,"image":"https://tintruyen.net/12390/fix-20/3.jpg?d=dfgd6546"},{"order":5,"image":"https://tintruyen.net/12390/fix-20/4.jpg?d=dfgd6546"},{"order":6,"image":"https://tintruyen.net/12390/fix-20/5.jpg?d=dfgd6546"},{"order":7,"image":"https://tintruyen.net/12390/fix-20/6.jpg?d=dfgd6546"},{"order":8,"image":"https://tintruyen.net/12390/fix-20/7.jpg?d=dfgd6546"},{"order":9,"image":"https://tintruyen.net/12390/fix-20/8.jpg?d=dfgd6546"},{"order":10,"image":"https://tintruyen.net/12390/fix-20/9.jpg?d=dfgd6546"},{"order":11,"image":"https://tintruyen.net/12390/fix-20/10.jpg?d=dfgd6546"},{"order":12,"image":"https://tintruyen.net/12390/fix-20/11.jpg?d=dfgd6546"},{"order":13,"image":"https://tintruyen.net/12390/fix-20/12.jpg?d=dfgd6546"},{"order":14,"image":"https://tintruyen.net/12390/fix-20/13.jpg?d=dfgd6546"},{"order":15,"image":"https://tintruyen.net/12390/fix-20/14.jpg?d=dfgd6546"},{"order":16,"image":"https://tintruyen.net/12390/fix-20/15.jpg?d=dfgd6546"},{"order":17,"image":"https://tintruyen.net/12390/fix-20/16.jpg?d=dfgd6546"},{"order":18,"image":"https://tintruyen.net/12390/fix-20/17.jpg?d=dfgd6546"},{"order":19,"image":"https://tintruyen.net/12390/fix-20/18.jpg?d=dfgd6546"},{"order":20,"image":"https://tintruyen.net/12390/fix-20/19.jpg?d=dfgd6546"},{"order":21,"image":"https://tintruyen.net/12390/fix-20/20.jpg?d=dfgd6546"},{"order":22,"image":"https://tintruyen.net/12390/fix-20/21.jpg?d=dfgd6546"},{"order":23,"image":"https://tintruyen.net/12390/fix-20/22.jpg?d=dfgd6546"},{"order":24,"image":"https://tintruyen.net/12390/fix-20/23.jpg?d=dfgd6546"},{"order":25,"image":"https://tintruyen.net/12390/fix-20/24.jpg?d=dfgd6546"},{"order":26,"image":"https://tintruyen.net/12390/fix-20/25.jpg?d=dfgd6546"},{"order":27,"image":"https://tintruyen.net/12390/fix-20/26.jpg?d=dfgd6546"},{"order":28,"image":"https://tintruyen.net/12390/fix-20/27.jpg?d=dfgd6546"},{"order":29,"image":"https://tintruyen.net/12390/fix-20/28.jpg?d=dfgd6546"},{"order":30,"image":"https://tintruyen.net/12390/fix-20/29.jpg?d=dfgd6546"},{"order":31,"image":"https://tintruyen.net/12390/fix-20/30.jpg?d=dfgd6546"},{"order":32,"image":"https://tintruyen.net/12390/fix-20/31.jpg?d=dfgd6546"},{"order":33,"image":"https://tintruyen.net/12390/fix-20/32.jpg?d=dfgd6546"}]},{"order":19,"name":"Chương 19","content":[{"order":1,"image":"https://tintruyen.net/12390/fix-19/0.jpg?d=dfgd6546"},{"order":2,"image":"https://tintruyen.net/12390/fix-19/1.jpg?d=dfgd6546"},{"order":3,"image":"https://tintruyen.net/12390/fix-19/2.jpg?d=dfgd6546"},{"order":4,"image":"https://tintruyen.net/12390/fix-19/3.jpg?d=dfgd6546"},{"order":5,"image":"https://tintruyen.net/12390/fix-19/4.jpg?d=dfgd6546"},{"order":6,"image":"https://tintruyen.net/12390/fix-19/5.jpg?d=dfgd6546"},{"order":7,"image":"https://tintruyen.net/12390/fix-19/6.jpg?d=dfgd6546"},{"order":8,"image":"https://tintruyen.net/12390/fix-19/7.jpg?d=dfgd6546"},{"order":9,"image":"https://tintruyen.net/12390/fix-19/8.jpg?d=dfgd6546"},{"order":10,"image":"https://tintruyen.net/12390/fix-19/9.jpg?d=dfgd6546"},{"order":11,"image":"https://tintruyen.net/12390/fix-19/10.jpg?d=dfgd6546"},{"order":12,"image":"https://tintruyen.net/12390/fix-19/11.jpg?d=dfgd6546"},{"order":13,"image":"https://tintruyen.net/12390/fix-19/12.jpg?d=dfgd6546"},{"order":14,"image":"https://tintruyen.net/12390/fix-19/13.jpg?d=dfgd6546"},{"order":15,"image":"https://tintruyen.net/12390/fix-19/14.jpg?d=dfgd6546"},{"order":16,"image":"https://tintruyen.net/12390/fix-19/15.jpg?d=dfgd6546"},{"order":17,"image":"https://tintruyen.net/12390/fix-19/16.jpg?d=dfgd6546"},{"order":18,"image":"https://tintruyen.net/12390/fix-19/17.jpg?d=dfgd6546"},{"order":19,"image":"https://tintruyen.net/12390/fix-19/18.jpg?d=dfgd6546"},{"order":20,"image":"https://tintruyen.net/12390/fix-19/19.jpg?d=dfgd6546"},{"order":21,"image":"https://tintruyen.net/12390/fix-19/20.jpg?d=dfgd6546"},{"order":22,"image":"https://tintruyen.net/12390/fix-19/21.jpg?d=dfgd6546"},{"order":23,"image":"https://tintruyen.net/12390/fix-19/22.jpg?d=dfgd6546"},{"order":24,"image":"https://tintruyen.net/12390/fix-19/23.jpg?d=dfgd6546"},{"order":25,"image":"https://tintruyen.net/12390/fix-19/24.jpg?d=dfgd6546"},{"order":26,"image":"https://tintruyen.net/12390/fix-19/25.jpg?d=dfgd6546"},{"order":27,"image":"https://tintruyen.net/12390/fix-19/26.jpg?d=dfgd6546"},{"order":28,"image":"https://tintruyen.net/12390/fix-19/27.jpg?d=dfgd6546"}]},{"order":18,"name":"Chương 18","content":[{"order":1,"image":"https://tintruyen.net/12390/18/0.jpg?d=dfgd6546"},{"order":2,"image":"https://tintruyen.net/12390/18/1.jpg?d=dfgd6546"},{"order":3,"image":"https://tintruyen.net/12390/18/2.jpg?d=dfgd6546"},{"order":4,"image":"https://tintruyen.net/12390/18/3.jpg?d=dfgd6546"},{"order":5,"image":"https://tintruyen.net/12390/18/4.jpg?d=dfgd6546"},{"order":6,"image":"https://tintruyen.net/12390/18/5.jpg?d=dfgd6546"},{"order":7,"image":"https://tintruyen.net/12390/18/6.jpg?d=dfgd6546"},{"order":8,"image":"https://tintruyen.net/12390/18/7.jpg?d=dfgd6546"},{"order":9,"image":"https://tintruyen.net/12390/18/8.jpg?d=dfgd6546"},{"order":10,"image":"https://tintruyen.net/12390/18/9.jpg?d=dfgd6546"},{"order":11,"image":"https://tintruyen.net/12390/18/10.jpg?d=dfgd6546"},{"order":12,"image":"https://tintruyen.net/12390/18/11.jpg?d=dfgd6546"},{"order":13,"image":"https://tintruyen.net/12390/18/12.jpg?d=dfgd6546"},{"order":14,"image":"https://tintruyen.net/12390/18/13.jpg?d=dfgd6546"},{"order":15,"image":"https://tintruyen.net/12390/18/14.jpg?d=dfgd6546"},{"order":16,"image":"https://tintruyen.net/12390/18/15.jpg?d=dfgd6546"},{"order":17,"image":"https://tintruyen.net/12390/18/16.jpg?d=dfgd6546"},{"order":18,"image":"https://tintruyen.net/12390/18/17.jpg?d=dfgd6546"},{"order":19,"image":"https://tintruyen.net/12390/18/18.jpg?d=dfgd6546"},{"order":20,"image":"https://tintruyen.net/12390/18/19.jpg?d=dfgd6546"},{"order":21,"image":"https://tintruyen.net/12390/18/20.jpg?d=dfgd6546"},{"order":22,"image":"https://tintruyen.net/12390/18/21.jpg?d=dfgd6546"},{"order":23,"image":"https://tintruyen.net/12390/18/22.jpg?d=dfgd6546"},{"order":24,"image":"https://tintruyen.net/12390/18/23.jpg?d=dfgd6546"},{"order":25,"image":"https://tintruyen.net/12390/18/24.jpg?d=dfgd6546"},{"order":26,"image":"https://tintruyen.net/12390/18/25.jpg?d=dfgd6546"},{"order":27,"image":"https://tintruyen.net/12390/18/26.jpg?d=dfgd6546"},{"order":28,"image":"https://tintruyen.net/12390/18/27.jpg?d=dfgd6546"},{"order":29,"image":"https://tintruyen.net/12390/18/28.jpg?d=dfgd6546"},{"order":30,"image":"https://tintruyen.net/12390/18/29.jpg?d=dfgd6546"},{"order":31,"image":"https://tintruyen.net/12390/18/30.jpg?d=dfgd6546"},{"order":32,"image":"https://tintruyen.net/12390/18/31.jpg?d=dfgd6546"},{"order":33,"image":"https://tintruyen.net/12390/18/32.jpg?d=dfgd6546"}]},{"order":17,"name":"Chương 17","content":[{"order":1,"image":"https://tintruyen.net/12390/fix-17/0.jpg?d=dfgd6546"},{"order":2,"image":"https://tintruyen.net/12390/fix-17/1.jpg?d=dfgd6546"},{"order":3,"image":"https://tintruyen.net/12390/fix-17/2.jpg?d=dfgd6546"},{"order":4,"image":"https://tintruyen.net/12390/fix-17/3.jpg?d=dfgd6546"},{"order":5,"image":"https://tintruyen.net/12390/fix-17/4.jpg?d=dfgd6546"},{"order":6,"image":"https://tintruyen.net/12390/fix-17/5.jpg?d=dfgd6546"},{"order":7,"image":"https://tintruyen.net/12390/fix-17/6.jpg?d=dfgd6546"},{"order":8,"image":"https://tintruyen.net/12390/fix-17/7.jpg?d=dfgd6546"},{"order":9,"image":"https://tintruyen.net/12390/fix-17/8.jpg?d=dfgd6546"},{"order":10,"image":"https://tintruyen.net/12390/fix-17/9.jpg?d=dfgd6546"},{"order":11,"image":"https://tintruyen.net/12390/fix-17/10.jpg?d=dfgd6546"},{"order":12,"image":"https://tintruyen.net/12390/fix-17/11.jpg?d=dfgd6546"},{"order":13,"image":"https://tintruyen.net/12390/fix-17/12.jpg?d=dfgd6546"},{"order":14,"image":"https://tintruyen.net/12390/fix-17/13.jpg?d=dfgd6546"},{"order":15,"image":"https://tintruyen.net/12390/fix-17/14.jpg?d=dfgd6546"},{"order":16,"image":"https://tintruyen.net/12390/fix-17/15.jpg?d=dfgd6546"},{"order":17,"image":"https://tintruyen.net/12390/fix-17/16.jpg?d=dfgd6546"},{"order":18,"image":"https://tintruyen.net/12390/fix-17/17.jpg?d=dfgd6546"},{"order":19,"image":"https://tintruyen.net/12390/fix-17/18.jpg?d=dfgd6546"},{"order":20,"image":"https://tintruyen.net/12390/fix-17/19.jpg?d=dfgd6546"}]},{"order":16,"name":"Chương 16","content":[{"order":1,"image":"https://tintruyen.net/12390/16/0.jpg?d=dfgd6546"},{"order":2,"image":"https://tintruyen.net/12390/16/1.jpg?d=dfgd6546"},{"order":3,"image":"https://tintruyen.net/12390/16/2.jpg?d=dfgd6546"},{"order":4,"image":"https://tintruyen.net/12390/16/3.jpg?d=dfgd6546"},{"order":5,"image":"https://tintruyen.net/12390/16/4.jpg?d=dfgd6546"},{"order":6,"image":"https://tintruyen.net/12390/16/5.jpg?d=dfgd6546"},{"order":7,"image":"https://tintruyen.net/12390/16/6.jpg?d=dfgd6546"},{"order":8,"image":"https://tintruyen.net/12390/16/7.jpg?d=dfgd6546"},{"order":9,"image":"https://tintruyen.net/12390/16/8.jpg?d=dfgd6546"},{"order":10,"image":"https://tintruyen.net/12390/16/9.jpg?d=dfgd6546"},{"order":11,"image":"https://tintruyen.net/12390/16/10.jpg?d=dfgd6546"},{"order":12,"image":"https://tintruyen.net/12390/16/11.jpg?d=dfgd6546"},{"order":13,"image":"https://tintruyen.net/12390/16/12.jpg?d=dfgd6546"},{"order":14,"image":"https://tintruyen.net/12390/16/13.jpg?d=dfgd6546"},{"order":15,"image":"https://tintruyen.net/12390/16/14.jpg?d=dfgd6546"},{"order":16,"image":"https://tintruyen.net/12390/16/15.jpg?d=dfgd6546"},{"order":17,"image":"https://tintruyen.net/12390/16/16.jpg?d=dfgd6546"},{"order":18,"image":"https://tintruyen.net/12390/16/17.jpg?d=dfgd6546"},{"order":19,"image":"https://tintruyen.net/12390/16/18.jpg?d=dfgd6546"},{"order":20,"image":"https://tintruyen.net/12390/16/19.jpg?d=dfgd6546"},{"order":21,"image":"https://tintruyen.net/12390/16/20.jpg?d=dfgd6546"},{"order":22,"image":"https://tintruyen.net/12390/16/21.jpg?d=dfgd6546"},{"order":23,"image":"https://tintruyen.net/12390/16/22.jpg?d=dfgd6546"},{"order":24,"image":"https://tintruyen.net/12390/16/23.jpg?d=dfgd6546"},{"order":25,"image":"https://tintruyen.net/12390/16/24.jpg?d=dfgd6546"},{"order":26,"image":"https://tintruyen.net/12390/16/25.jpg?d=dfgd6546"},{"order":27,"image":"https://tintruyen.net/12390/16/26.jpg?d=dfgd6546"},{"order":28,"image":"https://tintruyen.net/12390/16/27.jpg?d=dfgd6546"},{"order":29,"image":"https://tintruyen.net/12390/16/28.jpg?d=dfgd6546"},{"order":30,"image":"https://tintruyen.net/12390/16/29.jpg?d=dfgd6546"},{"order":31,"image":"https://tintruyen.net/12390/16/30.jpg?d=dfgd6546"},{"order":32,"image":"https://tintruyen.net/12390/16/31.jpg?d=dfgd6546"}]},{"order":15,"name":"Chương 15.1","content":[{"order":1,"image":"https://tintruyen.net/12390/fix-15.1/0.jpg?d=dfgd6546"},{"order":2,"image":"https://tintruyen.net/12390/fix-15.1/1.jpg?d=dfgd6546"},{"order":3,"image":"https://tintruyen.net/12390/fix-15.1/2.jpg?d=dfgd6546"},{"order":4,"image":"https://tintruyen.net/12390/fix-15.1/3.jpg?d=dfgd6546"},{"order":5,"image":"https://tintruyen.net/12390/fix-15.1/4.jpg?d=dfgd6546"},{"order":6,"image":"https://tintruyen.net/12390/fix-15.1/5.jpg?d=dfgd6546"},{"order":7,"image":"https://tintruyen.net/12390/fix-15.1/6.jpg?d=dfgd6546"},{"order":8,"image":"https://tintruyen.net/12390/fix-15.1/7.jpg?d=dfgd6546"},{"order":9,"image":"https://tintruyen.net/12390/fix-15.1/8.jpg?d=dfgd6546"},{"order":10,"image":"https://tintruyen.net/12390/fix-15.1/9.jpg?d=dfgd6546"},{"order":11,"image":"https://tintruyen.net/12390/fix-15.1/10.jpg?d=dfgd6546"},{"order":12,"image":"https://tintruyen.net/12390/fix-15.1/11.jpg?d=dfgd6546"},{"order":13,"image":"https://tintruyen.net/12390/fix-15.1/12.jpg?d=dfgd6546"},{"order":14,"image":"https://tintruyen.net/12390/fix-15.1/13.jpg?d=dfgd6546"},{"order":15,"image":"https://tintruyen.net/12390/fix-15.1/14.jpg?d=dfgd6546"},{"order":16,"image":"https://tintruyen.net/12390/fix-15.1/15.jpg?d=dfgd6546"},{"order":17,"image":"https://tintruyen.net/12390/fix-15.1/16.jpg?d=dfgd6546"},{"order":18,"image":"https://tintruyen.net/12390/fix-15.1/17.jpg?d=dfgd6546"},{"order":19,"image":"https://tintruyen.net/12390/fix-15.1/18.jpg?d=dfgd6546"},{"order":20,"image":"https://tintruyen.net/12390/fix-15.1/19.jpg?d=dfgd6546"},{"order":21,"image":"https://tintruyen.net/12390/fix-15.1/20.jpg?d=dfgd6546"},{"order":22,"image":"https://tintruyen.net/12390/fix-15.1/21.jpg?d=dfgd6546"}]},{"order":14,"name":"Chương 14","content":[{"order":1,"image":"https://tintruyen.net/12390/14/0.jpg?d=dfgd6546"},{"order":2,"image":"https://tintruyen.net/12390/14/1.jpg?d=dfgd6546"},{"order":3,"image":"https://tintruyen.net/12390/14/2.jpg?d=dfgd6546"},{"order":4,"image":"https://tintruyen.net/12390/14/3.jpg?d=dfgd6546"},{"order":5,"image":"https://tintruyen.net/12390/14/4.jpg?d=dfgd6546"},{"order":6,"image":"https://tintruyen.net/12390/14/5.jpg?d=dfgd6546"},{"order":7,"image":"https://tintruyen.net/12390/14/6.jpg?d=dfgd6546"},{"order":8,"image":"https://tintruyen.net/12390/14/7.jpg?d=dfgd6546"},{"order":9,"image":"https://tintruyen.net/12390/14/8.jpg?d=dfgd6546"},{"order":10,"image":"https://tintruyen.net/12390/14/9.jpg?d=dfgd6546"},{"order":11,"image":"https://tintruyen.net/12390/14/10.jpg?d=dfgd6546"},{"order":12,"image":"https://tintruyen.net/12390/14/11.jpg?d=dfgd6546"},{"order":13,"image":"https://tintruyen.net/12390/14/12.jpg?d=dfgd6546"},{"order":14,"image":"https://tintruyen.net/12390/14/13.jpg?d=dfgd6546"},{"order":15,"image":"https://tintruyen.net/12390/14/14.jpg?d=dfgd6546"},{"order":16,"image":"https://tintruyen.net/12390/14/15.jpg?d=dfgd6546"},{"order":17,"image":"https://tintruyen.net/12390/14/16.jpg?d=dfgd6546"},{"order":18,"image":"https://tintruyen.net/12390/14/17.jpg?d=dfgd6546"},{"order":19,"image":"https://tintruyen.net/12390/14/18.jpg?d=dfgd6546"},{"order":20,"image":"https://tintruyen.net/12390/14/19.jpg?d=dfgd6546"},{"order":21,"image":"https://tintruyen.net/12390/14/20.jpg?d=dfgd6546"},{"order":22,"image":"https://tintruyen.net/12390/14/21.jpg?d=dfgd6546"},{"order":23,"image":"https://tintruyen.net/12390/14/22.jpg?d=dfgd6546"},{"order":24,"image":"https://tintruyen.net/12390/14/23.jpg?d=dfgd6546"},{"order":25,"image":"https://tintruyen.net/12390/14/24.jpg?d=dfgd6546"},{"order":26,"image":"https://tintruyen.net/12390/14/25.jpg?d=dfgd6546"},{"order":27,"image":"https://tintruyen.net/12390/14/26.jpg?d=dfgd6546"},{"order":28,"image":"https://tintruyen.net/12390/14/27.jpg?d=dfgd6546"},{"order":29,"image":"https://tintruyen.net/12390/14/28.jpg?d=dfgd6546"},{"order":30,"image":"https://tintruyen.net/12390/14/29.jpg?d=dfgd6546"},{"order":31,"image":"https://tintruyen.net/12390/14/30.jpg?d=dfgd6546"},{"order":32,"image":"https://tintruyen.net/12390/14/31.jpg?d=dfgd6546"}]},{"order":13,"name":"Chương 13","content":[{"order":1,"image":"https://tintruyen.net/12390/13/0.jpg?d=dfgd6546"},{"order":2,"image":"https://tintruyen.net/12390/13/1.jpg?d=dfgd6546"},{"order":3,"image":"https://tintruyen.net/12390/13/2.jpg?d=dfgd6546"},{"order":4,"image":"https://tintruyen.net/12390/13/3.jpg?d=dfgd6546"},{"order":5,"image":"https://tintruyen.net/12390/13/4.jpg?d=dfgd6546"},{"order":6,"image":"https://tintruyen.net/12390/13/5.jpg?d=dfgd6546"},{"order":7,"image":"https://tintruyen.net/12390/13/6.jpg?d=dfgd6546"},{"order":8,"image":"https://tintruyen.net/12390/13/7.jpg?d=dfgd6546"},{"order":9,"image":"https://tintruyen.net/12390/13/8.jpg?d=dfgd6546"},{"order":10,"image":"https://tintruyen.net/12390/13/9.jpg?d=dfgd6546"},{"order":11,"image":"https://tintruyen.net/12390/13/10.jpg?d=dfgd6546"},{"order":12,"image":"https://tintruyen.net/12390/13/11.jpg?d=dfgd6546"},{"order":13,"image":"https://tintruyen.net/12390/13/12.jpg?d=dfgd6546"},{"order":14,"image":"https://tintruyen.net/12390/13/13.jpg?d=dfgd6546"},{"order":15,"image":"https://tintruyen.net/12390/13/14.jpg?d=dfgd6546"},{"order":16,"image":"https://tintruyen.net/12390/13/15.jpg?d=dfgd6546"},{"order":17,"image":"https://tintruyen.net/12390/13/16.jpg?d=dfgd6546"},{"order":18,"image":"https://tintruyen.net/12390/13/17.jpg?d=dfgd6546"},{"order":19,"image":"https://tintruyen.net/12390/13/18.jpg?d=dfgd6546"},{"order":20,"image":"https://tintruyen.net/12390/13/19.jpg?d=dfgd6546"},{"order":21,"image":"https://tintruyen.net/12390/13/20.jpg?d=dfgd6546"},{"order":22,"image":"https://tintruyen.net/12390/13/21.jpg?d=dfgd6546"},{"order":23,"image":"https://tintruyen.net/12390/13/22.jpg?d=dfgd6546"},{"order":24,"image":"https://tintruyen.net/12390/13/23.jpg?d=dfgd6546"},{"order":25,"image":"https://tintruyen.net/12390/13/24.jpg?d=dfgd6546"},{"order":26,"image":"https://tintruyen.net/12390/13/25.jpg?d=dfgd6546"},{"order":27,"image":"https://tintruyen.net/12390/13/26.jpg?d=dfgd6546"},{"order":28,"image":"https://tintruyen.net/12390/13/27.jpg?d=dfgd6546"},{"order":29,"image":"https://tintruyen.net/12390/13/28.jpg?d=dfgd6546"},{"order":30,"image":"https://tintruyen.net/12390/13/29.jpg?d=dfgd6546"}]},{"order":12,"name":"Chương 12","content":[{"order":1,"image":"https://tintruyen.net/12390/12/0.jpg?d=dfgd6546"},{"order":2,"image":"https://tintruyen.net/12390/12/1.jpg?d=dfgd6546"},{"order":3,"image":"https://tintruyen.net/12390/12/2.jpg?d=dfgd6546"},{"order":4,"image":"https://tintruyen.net/12390/12/3.jpg?d=dfgd6546"},{"order":5,"image":"https://tintruyen.net/12390/12/4.jpg?d=dfgd6546"},{"order":6,"image":"https://tintruyen.net/12390/12/5.jpg?d=dfgd6546"},{"order":7,"image":"https://tintruyen.net/12390/12/6.jpg?d=dfgd6546"},{"order":8,"image":"https://tintruyen.net/12390/12/7.jpg?d=dfgd6546"},{"order":9,"image":"https://tintruyen.net/12390/12/8.jpg?d=dfgd6546"},{"order":10,"image":"https://tintruyen.net/12390/12/9.jpg?d=dfgd6546"},{"order":11,"image":"https://tintruyen.net/12390/12/10.jpg?d=dfgd6546"},{"order":12,"image":"https://tintruyen.net/12390/12/11.jpg?d=dfgd6546"},{"order":13,"image":"https://tintruyen.net/12390/12/12.jpg?d=dfgd6546"},{"order":14,"image":"https://tintruyen.net/12390/12/13.jpg?d=dfgd6546"},{"order":15,"image":"https://tintruyen.net/12390/12/14.jpg?d=dfgd6546"},{"order":16,"image":"https://tintruyen.net/12390/12/15.jpg?d=dfgd6546"},{"order":17,"image":"https://tintruyen.net/12390/12/16.jpg?d=dfgd6546"},{"order":18,"image":"https://tintruyen.net/12390/12/17.jpg?d=dfgd6546"},{"order":19,"image":"https://tintruyen.net/12390/12/18.jpg?d=dfgd6546"},{"order":20,"image":"https://tintruyen.net/12390/12/19.jpg?d=dfgd6546"},{"order":21,"image":"https://tintruyen.net/12390/12/20.jpg?d=dfgd6546"},{"order":22,"image":"https://tintruyen.net/12390/12/21.jpg?d=dfgd6546"},{"order":23,"image":"https://tintruyen.net/12390/12/22.jpg?d=dfgd6546"},{"order":24,"image":"https://tintruyen.net/12390/12/23.jpg?d=dfgd6546"},{"order":25,"image":"https://tintruyen.net/12390/12/24.jpg?d=dfgd6546"},{"order":26,"image":"https://tintruyen.net/12390/12/25.jpg?d=dfgd6546"},{"order":27,"image":"https://tintruyen.net/12390/12/26.jpg?d=dfgd6546"},{"order":28,"image":"https://tintruyen.net/12390/12/27.jpg?d=dfgd6546"},{"order":29,"image":"https://tintruyen.net/12390/12/28.jpg?d=dfgd6546"},{"order":30,"image":"https://tintruyen.net/12390/12/29.jpg?d=dfgd6546"},{"order":31,"image":"https://tintruyen.net/12390/12/30.jpg?d=dfgd6546"},{"order":32,"image":"https://tintruyen.net/12390/12/31.jpg?d=dfgd6546"}]},{"order":11,"name":"Chương 11","content":[{"order":1,"image":"https://tintruyen.net/12390/fix-11/0.jpg?d=dfgd6546"},{"order":2,"image":"https://tintruyen.net/12390/fix-11/1.jpg?d=dfgd6546"},{"order":3,"image":"https://tintruyen.net/12390/fix-11/2.jpg?d=dfgd6546"},{"order":4,"image":"https://tintruyen.net/12390/fix-11/3.jpg?d=dfgd6546"},{"order":5,"image":"https://tintruyen.net/12390/fix-11/4.jpg?d=dfgd6546"},{"order":6,"image":"https://tintruyen.net/12390/fix-11/5.jpg?d=dfgd6546"},{"order":7,"image":"https://tintruyen.net/12390/fix-11/6.jpg?d=dfgd6546"},{"order":8,"image":"https://tintruyen.net/12390/fix-11/7.jpg?d=dfgd6546"},{"order":9,"image":"https://tintruyen.net/12390/fix-11/8.jpg?d=dfgd6546"},{"order":10,"image":"https://tintruyen.net/12390/fix-11/9.jpg?d=dfgd6546"},{"order":11,"image":"https://tintruyen.net/12390/fix-11/10.jpg?d=dfgd6546"},{"order":12,"image":"https://tintruyen.net/12390/fix-11/11.jpg?d=dfgd6546"},{"order":13,"image":"https://tintruyen.net/12390/fix-11/12.jpg?d=dfgd6546"},{"order":14,"image":"https://tintruyen.net/12390/fix-11/13.jpg?d=dfgd6546"},{"order":15,"image":"https://tintruyen.net/12390/fix-11/14.jpg?d=dfgd6546"},{"order":16,"image":"https://tintruyen.net/12390/fix-11/15.jpg?d=dfgd6546"},{"order":17,"image":"https://tintruyen.net/12390/fix-11/16.jpg?d=dfgd6546"},{"order":18,"image":"https://tintruyen.net/12390/fix-11/17.jpg?d=dfgd6546"},{"order":19,"image":"https://tintruyen.net/12390/fix-11/18.jpg?d=dfgd6546"},{"order":20,"image":"https://tintruyen.net/12390/fix-11/19.jpg?d=dfgd6546"},{"order":21,"image":"https://tintruyen.net/12390/fix-11/20.jpg?d=dfgd6546"}]},{"order":10,"name":"Chương 10","content":[{"order":1,"image":"https://tintruyen.net/12390/fix-10/0.jpg?d=dfgd6546"},{"order":2,"image":"https://tintruyen.net/12390/fix-10/1.jpg?d=dfgd6546"},{"order":3,"image":"https://tintruyen.net/12390/fix-10/2.jpg?d=dfgd6546"},{"order":4,"image":"https://tintruyen.net/12390/fix-10/3.jpg?d=dfgd6546"},{"order":5,"image":"https://tintruyen.net/12390/fix-10/4.jpg?d=dfgd6546"},{"order":6,"image":"https://tintruyen.net/12390/fix-10/5.jpg?d=dfgd6546"},{"order":7,"image":"https://tintruyen.net/12390/fix-10/6.jpg?d=dfgd6546"},{"order":8,"image":"https://tintruyen.net/12390/fix-10/7.jpg?d=dfgd6546"},{"order":9,"image":"https://tintruyen.net/12390/fix-10/8.jpg?d=dfgd6546"},{"order":10,"image":"https://tintruyen.net/12390/fix-10/9.jpg?d=dfgd6546"},{"order":11,"image":"https://tintruyen.net/12390/fix-10/10.jpg?d=dfgd6546"},{"order":12,"image":"https://tintruyen.net/12390/fix-10/11.jpg?d=dfgd6546"},{"order":13,"image":"https://tintruyen.net/12390/fix-10/12.jpg?d=dfgd6546"},{"order":14,"image":"https://tintruyen.net/12390/fix-10/13.jpg?d=dfgd6546"},{"order":15,"image":"https://tintruyen.net/12390/fix-10/14.jpg?d=dfgd6546"},{"order":16,"image":"https://tintruyen.net/12390/fix-10/15.jpg?d=dfgd6546"},{"order":17,"image":"https://tintruyen.net/12390/fix-10/16.jpg?d=dfgd6546"},{"order":18,"image":"https://tintruyen.net/12390/fix-10/17.jpg?d=dfgd6546"},{"order":19,"image":"https://tintruyen.net/12390/fix-10/18.jpg?d=dfgd6546"},{"order":20,"image":"https://tintruyen.net/12390/fix-10/19.jpg?d=dfgd6546"},{"order":21,"image":"https://tintruyen.net/12390/fix-10/20.jpg?d=dfgd6546"},{"order":22,"image":"https://tintruyen.net/12390/fix-10/21.jpg?d=dfgd6546"},{"order":23,"image":"https://tintruyen.net/12390/fix-10/22.jpg?d=dfgd6546"},{"order":24,"image":"https://tintruyen.net/12390/fix-10/23.jpg?d=dfgd6546"},{"order":25,"image":"https://tintruyen.net/12390/fix-10/24.jpg?d=dfgd6546"},{"order":26,"image":"https://tintruyen.net/12390/fix-10/25.jpg?d=dfgd6546"}]},{"order":9,"name":"Chương 9","content":[{"order":1,"image":"https://tintruyen.net/12390/fix-9/0.jpg?d=dfgd6546"},{"order":2,"image":"https://tintruyen.net/12390/fix-9/1.jpg?d=dfgd6546"},{"order":3,"image":"https://tintruyen.net/12390/fix-9/2.jpg?d=dfgd6546"},{"order":4,"image":"https://tintruyen.net/12390/fix-9/3.jpg?d=dfgd6546"},{"order":5,"image":"https://tintruyen.net/12390/fix-9/4.jpg?d=dfgd6546"},{"order":6,"image":"https://tintruyen.net/12390/fix-9/5.jpg?d=dfgd6546"},{"order":7,"image":"https://tintruyen.net/12390/fix-9/6.jpg?d=dfgd6546"},{"order":8,"image":"https://tintruyen.net/12390/fix-9/7.jpg?d=dfgd6546"},{"order":9,"image":"https://tintruyen.net/12390/fix-9/8.jpg?d=dfgd6546"},{"order":10,"image":"https://tintruyen.net/12390/fix-9/9.jpg?d=dfgd6546"},{"order":11,"image":"https://tintruyen.net/12390/fix-9/10.jpg?d=dfgd6546"},{"order":12,"image":"https://tintruyen.net/12390/fix-9/11.jpg?d=dfgd6546"},{"order":13,"image":"https://tintruyen.net/12390/fix-9/12.jpg?d=dfgd6546"},{"order":14,"image":"https://tintruyen.net/12390/fix-9/13.jpg?d=dfgd6546"},{"order":15,"image":"https://tintruyen.net/12390/fix-9/14.jpg?d=dfgd6546"},{"order":16,"image":"https://tintruyen.net/12390/fix-9/15.jpg?d=dfgd6546"},{"order":17,"image":"https://tintruyen.net/12390/fix-9/16.jpg?d=dfgd6546"},{"order":18,"image":"https://tintruyen.net/12390/fix-9/17.jpg?d=dfgd6546"},{"order":19,"image":"https://tintruyen.net/12390/fix-9/18.jpg?d=dfgd6546"},{"order":20,"image":"https://tintruyen.net/12390/fix-9/19.jpg?d=dfgd6546"},{"order":21,"image":"https://tintruyen.net/12390/fix-9/20.jpg?d=dfgd6546"},{"order":22,"image":"https://tintruyen.net/12390/fix-9/21.jpg?d=dfgd6546"},{"order":23,"image":"https://tintruyen.net/12390/fix-9/22.jpg?d=dfgd6546"},{"order":24,"image":"https://tintruyen.net/12390/fix-9/23.jpg?d=dfgd6546"},{"order":25,"image":"https://tintruyen.net/12390/fix-9/24.jpg?d=dfgd6546"},{"order":26,"image":"https://tintruyen.net/12390/fix-9/25.jpg?d=dfgd6546"},{"order":27,"image":"https://tintruyen.net/12390/fix-9/26.jpg?d=dfgd6546"},{"order":28,"image":"https://tintruyen.net/12390/fix-9/27.jpg?d=dfgd6546"}]},{"order":8,"name":"Chương 8","content":[{"order":1,"image":"https://tintruyen.net/12390/fix-8/0.jpg?d=dfgd6546"},{"order":2,"image":"https://tintruyen.net/12390/fix-8/1.jpg?d=dfgd6546"},{"order":3,"image":"https://tintruyen.net/12390/fix-8/2.jpg?d=dfgd6546"},{"order":4,"image":"https://tintruyen.net/12390/fix-8/3.jpg?d=dfgd6546"},{"order":5,"image":"https://tintruyen.net/12390/fix-8/4.jpg?d=dfgd6546"},{"order":6,"image":"https://tintruyen.net/12390/fix-8/5.jpg?d=dfgd6546"},{"order":7,"image":"https://tintruyen.net/12390/fix-8/6.jpg?d=dfgd6546"},{"order":8,"image":"https://tintruyen.net/12390/fix-8/7.jpg?d=dfgd6546"},{"order":9,"image":"https://tintruyen.net/12390/fix-8/8.jpg?d=dfgd6546"},{"order":10,"image":"https://tintruyen.net/12390/fix-8/9.jpg?d=dfgd6546"},{"order":11,"image":"https://tintruyen.net/12390/fix-8/10.jpg?d=dfgd6546"},{"order":12,"image":"https://tintruyen.net/12390/fix-8/11.jpg?d=dfgd6546"},{"order":13,"image":"https://tintruyen.net/12390/fix-8/12.jpg?d=dfgd6546"},{"order":14,"image":"https://tintruyen.net/12390/fix-8/13.jpg?d=dfgd6546"},{"order":15,"image":"https://tintruyen.net/12390/fix-8/14.jpg?d=dfgd6546"},{"order":16,"image":"https://tintruyen.net/12390/fix-8/15.jpg?d=dfgd6546"},{"order":17,"image":"https://tintruyen.net/12390/fix-8/16.jpg?d=dfgd6546"},{"order":18,"image":"https://tintruyen.net/12390/fix-8/17.jpg?d=dfgd6546"},{"order":19,"image":"https://tintruyen.net/12390/fix-8/18.jpg?d=dfgd6546"},{"order":20,"image":"https://tintruyen.net/12390/fix-8/19.jpg?d=dfgd6546"},{"order":21,"image":"https://tintruyen.net/12390/fix-8/20.jpg?d=dfgd6546"},{"order":22,"image":"https://tintruyen.net/12390/fix-8/21.jpg?d=dfgd6546"},{"order":23,"image":"https://tintruyen.net/12390/fix-8/22.jpg?d=dfgd6546"},{"order":24,"image":"https://tintruyen.net/12390/fix-8/23.jpg?d=dfgd6546"}]},{"order":7,"name":"Chương 7","content":[{"order":1,"image":"https://tintruyen.net/12390/fix-7/0.jpg?d=dfgd6546"},{"order":2,"image":"https://tintruyen.net/12390/fix-7/1.jpg?d=dfgd6546"},{"order":3,"image":"https://tintruyen.net/12390/fix-7/2.jpg?d=dfgd6546"},{"order":4,"image":"https://tintruyen.net/12390/fix-7/3.jpg?d=dfgd6546"},{"order":5,"image":"https://tintruyen.net/12390/fix-7/4.jpg?d=dfgd6546"},{"order":6,"image":"https://tintruyen.net/12390/fix-7/5.jpg?d=dfgd6546"},{"order":7,"image":"https://tintruyen.net/12390/fix-7/6.jpg?d=dfgd6546"},{"order":8,"image":"https://tintruyen.net/12390/fix-7/7.jpg?d=dfgd6546"},{"order":9,"image":"https://tintruyen.net/12390/fix-7/8.jpg?d=dfgd6546"},{"order":10,"image":"https://tintruyen.net/12390/fix-7/9.jpg?d=dfgd6546"},{"order":11,"image":"https://tintruyen.net/12390/fix-7/10.jpg?d=dfgd6546"},{"order":12,"image":"https://tintruyen.net/12390/fix-7/11.jpg?d=dfgd6546"},{"order":13,"image":"https://tintruyen.net/12390/fix-7/12.jpg?d=dfgd6546"},{"order":14,"image":"https://tintruyen.net/12390/fix-7/13.jpg?d=dfgd6546"},{"order":15,"image":"https://tintruyen.net/12390/fix-7/14.jpg?d=dfgd6546"},{"order":16,"image":"https://tintruyen.net/12390/fix-7/15.jpg?d=dfgd6546"},{"order":17,"image":"https://tintruyen.net/12390/fix-7/16.jpg?d=dfgd6546"},{"order":18,"image":"https://tintruyen.net/12390/fix-7/17.jpg?d=dfgd6546"},{"order":19,"image":"https://tintruyen.net/12390/fix-7/18.jpg?d=dfgd6546"},{"order":20,"image":"https://tintruyen.net/12390/fix-7/19.jpg?d=dfgd6546"},{"order":21,"image":"https://tintruyen.net/12390/fix-7/20.jpg?d=dfgd6546"},{"order":22,"image":"https://tintruyen.net/12390/fix-7/21.jpg?d=dfgd6546"},{"order":23,"image":"https://tintruyen.net/12390/fix-7/22.jpg?d=dfgd6546"},{"order":24,"image":"https://tintruyen.net/12390/fix-7/23.jpg?d=dfgd6546"},{"order":25,"image":"https://tintruyen.net/12390/fix-7/24.jpg?d=dfgd6546"},{"order":26,"image":"https://tintruyen.net/12390/fix-7/25.jpg?d=dfgd6546"},{"order":27,"image":"https://tintruyen.net/12390/fix-7/26.jpg?d=dfgd6546"},{"order":28,"image":"https://tintruyen.net/12390/fix-7/27.jpg?d=dfgd6546"},{"order":29,"image":"https://tintruyen.net/12390/fix-7/28.jpg?d=dfgd6546"},{"order":30,"image":"https://tintruyen.net/12390/fix-7/29.jpg?d=dfgd6546"},{"order":31,"image":"https://tintruyen.net/12390/fix-7/30.jpg?d=dfgd6546"}]},{"order":6,"name":"Chương 6","content":[{"order":1,"image":"https://tintruyen.net/12390/fix-6/0.jpg?d=dfgd6546"},{"order":2,"image":"https://tintruyen.net/12390/fix-6/1.jpg?d=dfgd6546"},{"order":3,"image":"https://tintruyen.net/12390/fix-6/2.jpg?d=dfgd6546"},{"order":4,"image":"https://tintruyen.net/12390/fix-6/3.jpg?d=dfgd6546"},{"order":5,"image":"https://tintruyen.net/12390/fix-6/4.jpg?d=dfgd6546"},{"order":6,"image":"https://tintruyen.net/12390/fix-6/5.jpg?d=dfgd6546"},{"order":7,"image":"https://tintruyen.net/12390/fix-6/6.jpg?d=dfgd6546"},{"order":8,"image":"https://tintruyen.net/12390/fix-6/7.jpg?d=dfgd6546"},{"order":9,"image":"https://tintruyen.net/12390/fix-6/8.jpg?d=dfgd6546"},{"order":10,"image":"https://tintruyen.net/12390/fix-6/9.jpg?d=dfgd6546"},{"order":11,"image":"https://tintruyen.net/12390/fix-6/10.jpg?d=dfgd6546"},{"order":12,"image":"https://tintruyen.net/12390/fix-6/11.jpg?d=dfgd6546"},{"order":13,"image":"https://tintruyen.net/12390/fix-6/12.jpg?d=dfgd6546"},{"order":14,"image":"https://tintruyen.net/12390/fix-6/13.jpg?d=dfgd6546"},{"order":15,"image":"https://tintruyen.net/12390/fix-6/14.jpg?d=dfgd6546"},{"order":16,"image":"https://tintruyen.net/12390/fix-6/15.jpg?d=dfgd6546"},{"order":17,"image":"https://tintruyen.net/12390/fix-6/16.jpg?d=dfgd6546"},{"order":18,"image":"https://tintruyen.net/12390/fix-6/17.jpg?d=dfgd6546"},{"order":19,"image":"https://tintruyen.net/12390/fix-6/18.jpg?d=dfgd6546"},{"order":20,"image":"https://tintruyen.net/12390/fix-6/19.jpg?d=dfgd6546"},{"order":21,"image":"https://tintruyen.net/12390/fix-6/20.jpg?d=dfgd6546"},{"order":22,"image":"https://tintruyen.net/12390/fix-6/21.jpg?d=dfgd6546"},{"order":23,"image":"https://tintruyen.net/12390/fix-6/22.jpg?d=dfgd6546"},{"order":24,"image":"https://tintruyen.net/12390/fix-6/23.jpg?d=dfgd6546"},{"order":25,"image":"https://tintruyen.net/12390/fix-6/24.jpg?d=dfgd6546"},{"order":26,"image":"https://tintruyen.net/12390/fix-6/25.jpg?d=dfgd6546"},{"order":27,"image":"https://tintruyen.net/12390/fix-6/26.jpg?d=dfgd6546"},{"order":28,"image":"https://tintruyen.net/12390/fix-6/27.jpg?d=dfgd6546"},{"order":29,"image":"https://tintruyen.net/12390/fix-6/28.jpg?d=dfgd6546"},{"order":30,"image":"https://tintruyen.net/12390/fix-6/29.jpg?d=dfgd6546"},{"order":31,"image":"https://tintruyen.net/12390/fix-6/30.jpg?d=dfgd6546"},{"order":32,"image":"https://tintruyen.net/12390/fix-6/31.jpg?d=dfgd6546"},{"order":33,"image":"https://tintruyen.net/12390/fix-6/32.jpg?d=dfgd6546"},{"order":34,"image":"https://tintruyen.net/12390/fix-6/33.jpg?d=dfgd6546"}]},{"order":5,"name":"Chương 5","content":[{"order":1,"image":"https://tintruyen.net/12390/fix-5/0.jpg?d=dfgd6546"},{"order":2,"image":"https://tintruyen.net/12390/fix-5/1.jpg?d=dfgd6546"},{"order":3,"image":"https://tintruyen.net/12390/fix-5/2.jpg?d=dfgd6546"},{"order":4,"image":"https://tintruyen.net/12390/fix-5/3.jpg?d=dfgd6546"},{"order":5,"image":"https://tintruyen.net/12390/fix-5/4.jpg?d=dfgd6546"},{"order":6,"image":"https://tintruyen.net/12390/fix-5/5.jpg?d=dfgd6546"},{"order":7,"image":"https://tintruyen.net/12390/fix-5/6.jpg?d=dfgd6546"},{"order":8,"image":"https://tintruyen.net/12390/fix-5/7.jpg?d=dfgd6546"},{"order":9,"image":"https://tintruyen.net/12390/fix-5/8.jpg?d=dfgd6546"},{"order":10,"image":"https://tintruyen.net/12390/fix-5/9.jpg?d=dfgd6546"},{"order":11,"image":"https://tintruyen.net/12390/fix-5/10.jpg?d=dfgd6546"},{"order":12,"image":"https://tintruyen.net/12390/fix-5/11.jpg?d=dfgd6546"},{"order":13,"image":"https://tintruyen.net/12390/fix-5/12.jpg?d=dfgd6546"},{"order":14,"image":"https://tintruyen.net/12390/fix-5/13.jpg?d=dfgd6546"},{"order":15,"image":"https://tintruyen.net/12390/fix-5/14.jpg?d=dfgd6546"},{"order":16,"image":"https://tintruyen.net/12390/fix-5/15.jpg?d=dfgd6546"},{"order":17,"image":"https://tintruyen.net/12390/fix-5/16.jpg?d=dfgd6546"},{"order":18,"image":"https://tintruyen.net/12390/fix-5/17.jpg?d=dfgd6546"},{"order":19,"image":"https://tintruyen.net/12390/fix-5/18.jpg?d=dfgd6546"},{"order":20,"image":"https://tintruyen.net/12390/fix-5/19.jpg?d=dfgd6546"},{"order":21,"image":"https://tintruyen.net/12390/fix-5/20.jpg?d=dfgd6546"},{"order":22,"image":"https://tintruyen.net/12390/fix-5/21.jpg?d=dfgd6546"},{"order":23,"image":"https://tintruyen.net/12390/fix-5/22.jpg?d=dfgd6546"},{"order":24,"image":"https://tintruyen.net/12390/fix-5/23.jpg?d=dfgd6546"},{"order":25,"image":"https://tintruyen.net/12390/fix-5/24.jpg?d=dfgd6546"},{"order":26,"image":"https://tintruyen.net/12390/fix-5/25.jpg?d=dfgd6546"},{"order":27,"image":"https://tintruyen.net/12390/fix-5/26.jpg?d=dfgd6546"},{"order":28,"image":"https://tintruyen.net/12390/fix-5/27.jpg?d=dfgd6546"}]},{"order":4,"name":"Chương 4","content":[{"order":1,"image":"https://tintruyen.net/12390/fix-4/0.jpg?d=dfgd6546"},{"order":2,"image":"https://tintruyen.net/12390/fix-4/1.jpg?d=dfgd6546"},{"order":3,"image":"https://tintruyen.net/12390/fix-4/2.jpg?d=dfgd6546"},{"order":4,"image":"https://tintruyen.net/12390/fix-4/3.jpg?d=dfgd6546"},{"order":5,"image":"https://tintruyen.net/12390/fix-4/4.jpg?d=dfgd6546"},{"order":6,"image":"https://tintruyen.net/12390/fix-4/5.jpg?d=dfgd6546"},{"order":7,"image":"https://tintruyen.net/12390/fix-4/6.jpg?d=dfgd6546"},{"order":8,"image":"https://tintruyen.net/12390/fix-4/7.jpg?d=dfgd6546"},{"order":9,"image":"https://tintruyen.net/12390/fix-4/8.jpg?d=dfgd6546"},{"order":10,"image":"https://tintruyen.net/12390/fix-4/9.jpg?d=dfgd6546"},{"order":11,"image":"https://tintruyen.net/12390/fix-4/10.jpg?d=dfgd6546"},{"order":12,"image":"https://tintruyen.net/12390/fix-4/11.jpg?d=dfgd6546"},{"order":13,"image":"https://tintruyen.net/12390/fix-4/12.jpg?d=dfgd6546"},{"order":14,"image":"https://tintruyen.net/12390/fix-4/13.jpg?d=dfgd6546"},{"order":15,"image":"https://tintruyen.net/12390/fix-4/14.jpg?d=dfgd6546"},{"order":16,"image":"https://tintruyen.net/12390/fix-4/15.jpg?d=dfgd6546"},{"order":17,"image":"https://tintruyen.net/12390/fix-4/16.jpg?d=dfgd6546"},{"order":18,"image":"https://tintruyen.net/12390/fix-4/17.jpg?d=dfgd6546"},{"order":19,"image":"https://tintruyen.net/12390/fix-4/18.jpg?d=dfgd6546"},{"order":20,"image":"https://tintruyen.net/12390/fix-4/19.jpg?d=dfgd6546"},{"order":21,"image":"https://tintruyen.net/12390/fix-4/20.jpg?d=dfgd6546"},{"order":22,"image":"https://tintruyen.net/12390/fix-4/21.jpg?d=dfgd6546"},{"order":23,"image":"https://tintruyen.net/12390/fix-4/22.jpg?d=dfgd6546"},{"order":24,"image":"https://tintruyen.net/12390/fix-4/23.jpg?d=dfgd6546"},{"order":25,"image":"https://tintruyen.net/12390/fix-4/24.jpg?d=dfgd6546"},{"order":26,"image":"https://tintruyen.net/12390/fix-4/25.jpg?d=dfgd6546"},{"order":27,"image":"https://tintruyen.net/12390/fix-4/26.jpg?d=dfgd6546"},{"order":28,"image":"https://tintruyen.net/12390/fix-4/27.jpg?d=dfgd6546"},{"order":29,"image":"https://tintruyen.net/12390/fix-4/28.jpg?d=dfgd6546"}]},{"order":3,"name":"Chương 3","content":[{"order":1,"image":"https://tintruyen.net/12390/fix-3/0.jpg?d=dfgd6546"},{"order":2,"image":"https://tintruyen.net/12390/fix-3/1.jpg?d=dfgd6546"},{"order":3,"image":"https://tintruyen.net/12390/fix-3/2.jpg?d=dfgd6546"},{"order":4,"image":"https://tintruyen.net/12390/fix-3/3.jpg?d=dfgd6546"},{"order":5,"image":"https://tintruyen.net/12390/fix-3/4.jpg?d=dfgd6546"},{"order":6,"image":"https://tintruyen.net/12390/fix-3/5.jpg?d=dfgd6546"},{"order":7,"image":"https://tintruyen.net/12390/fix-3/6.jpg?d=dfgd6546"},{"order":8,"image":"https://tintruyen.net/12390/fix-3/7.jpg?d=dfgd6546"},{"order":9,"image":"https://tintruyen.net/12390/fix-3/8.jpg?d=dfgd6546"},{"order":10,"image":"https://tintruyen.net/12390/fix-3/9.jpg?d=dfgd6546"},{"order":11,"image":"https://tintruyen.net/12390/fix-3/10.jpg?d=dfgd6546"},{"order":12,"image":"https://tintruyen.net/12390/fix-3/11.jpg?d=dfgd6546"},{"order":13,"image":"https://tintruyen.net/12390/fix-3/12.jpg?d=dfgd6546"},{"order":14,"image":"https://tintruyen.net/12390/fix-3/13.jpg?d=dfgd6546"},{"order":15,"image":"https://tintruyen.net/12390/fix-3/14.jpg?d=dfgd6546"},{"order":16,"image":"https://tintruyen.net/12390/fix-3/15.jpg?d=dfgd6546"},{"order":17,"image":"https://tintruyen.net/12390/fix-3/16.jpg?d=dfgd6546"},{"order":18,"image":"https://tintruyen.net/12390/fix-3/17.jpg?d=dfgd6546"},{"order":19,"image":"https://tintruyen.net/12390/fix-3/18.jpg?d=dfgd6546"},{"order":20,"image":"https://tintruyen.net/12390/fix-3/19.jpg?d=dfgd6546"},{"order":21,"image":"https://tintruyen.net/12390/fix-3/20.jpg?d=dfgd6546"},{"order":22,"image":"https://tintruyen.net/12390/fix-3/21.jpg?d=dfgd6546"},{"order":23,"image":"https://tintruyen.net/12390/fix-3/22.jpg?d=dfgd6546"},{"order":24,"image":"https://tintruyen.net/12390/fix-3/23.jpg?d=dfgd6546"},{"order":25,"image":"https://tintruyen.net/12390/fix-3/24.jpg?d=dfgd6546"},{"order":26,"image":"https://tintruyen.net/12390/fix-3/25.jpg?d=dfgd6546"},{"order":27,"image":"https://tintruyen.net/12390/fix-3/26.jpg?d=dfgd6546"},{"order":28,"image":"https://tintruyen.net/12390/fix-3/27.jpg?d=dfgd6546"},{"order":29,"image":"https://tintruyen.net/12390/fix-3/28.jpg?d=dfgd6546"},{"order":30,"image":"https://tintruyen.net/12390/fix-3/29.jpg?d=dfgd6546"},{"order":31,"image":"https://tintruyen.net/12390/fix-3/30.jpg?d=dfgd6546"},{"order":32,"image":"https://tintruyen.net/12390/fix-3/31.jpg?d=dfgd6546"}]},{"order":2,"name":"Chương 2","content":[{"order":1,"image":"https://tintruyen.net/12390/fix-2/0.jpg?d=dfgd6546"},{"order":2,"image":"https://tintruyen.net/12390/fix-2/1.jpg?d=dfgd6546"},{"order":3,"image":"https://tintruyen.net/12390/fix-2/2.jpg?d=dfgd6546"},{"order":4,"image":"https://tintruyen.net/12390/fix-2/3.jpg?d=dfgd6546"},{"order":5,"image":"https://tintruyen.net/12390/fix-2/4.jpg?d=dfgd6546"},{"order":6,"image":"https://tintruyen.net/12390/fix-2/5.jpg?d=dfgd6546"},{"order":7,"image":"https://tintruyen.net/12390/fix-2/6.jpg?d=dfgd6546"},{"order":8,"image":"https://tintruyen.net/12390/fix-2/7.jpg?d=dfgd6546"},{"order":9,"image":"https://tintruyen.net/12390/fix-2/8.jpg?d=dfgd6546"},{"order":10,"image":"https://tintruyen.net/12390/fix-2/9.jpg?d=dfgd6546"},{"order":11,"image":"https://tintruyen.net/12390/fix-2/10.jpg?d=dfgd6546"},{"order":12,"image":"https://tintruyen.net/12390/fix-2/11.jpg?d=dfgd6546"},{"order":13,"image":"https://tintruyen.net/12390/fix-2/12.jpg?d=dfgd6546"},{"order":14,"image":"https://tintruyen.net/12390/fix-2/13.jpg?d=dfgd6546"},{"order":15,"image":"https://tintruyen.net/12390/fix-2/14.jpg?d=dfgd6546"},{"order":16,"image":"https://tintruyen.net/12390/fix-2/15.jpg?d=dfgd6546"},{"order":17,"image":"https://tintruyen.net/12390/fix-2/16.jpg?d=dfgd6546"},{"order":18,"image":"https://tintruyen.net/12390/fix-2/17.jpg?d=dfgd6546"},{"order":19,"image":"https://tintruyen.net/12390/fix-2/18.jpg?d=dfgd6546"},{"order":20,"image":"https://tintruyen.net/12390/fix-2/19.jpg?d=dfgd6546"},{"order":21,"image":"https://tintruyen.net/12390/fix-2/20.jpg?d=dfgd6546"},{"order":22,"image":"https://tintruyen.net/12390/fix-2/21.jpg?d=dfgd6546"},{"order":23,"image":"https://tintruyen.net/12390/fix-2/22.jpg?d=dfgd6546"},{"order":24,"image":"https://tintruyen.net/12390/fix-2/23.jpg?d=dfgd6546"},{"order":25,"image":"https://tintruyen.net/12390/fix-2/24.jpg?d=dfgd6546"},{"order":26,"image":"https://tintruyen.net/12390/fix-2/25.jpg?d=dfgd6546"},{"order":27,"image":"https://tintruyen.net/12390/fix-2/26.jpg?d=dfgd6546"},{"order":28,"image":"https://tintruyen.net/12390/fix-2/27.jpg?d=dfgd6546"},{"order":29,"image":"https://tintruyen.net/12390/fix-2/28.jpg?d=dfgd6546"},{"order":30,"image":"https://tintruyen.net/12390/fix-2/29.jpg?d=dfgd6546"},{"order":31,"image":"https://tintruyen.net/12390/fix-2/30.jpg?d=dfgd6546"}]},{"order":1,"name":"Chương 1","content":[{"order":1,"image":"https://tintruyen.net/12390/fix-1/0.jpg?d=dfgd6546"},{"order":2,"image":"https://tintruyen.net/12390/fix-1/1.jpg?d=dfgd6546"},{"order":3,"image":"https://tintruyen.net/12390/fix-1/2.jpg?d=dfgd6546"},{"order":4,"image":"https://tintruyen.net/12390/fix-1/3.jpg?d=dfgd6546"},{"order":5,"image":"https://tintruyen.net/12390/fix-1/4.jpg?d=dfgd6546"},{"order":6,"image":"https://tintruyen.net/12390/fix-1/5.jpg?d=dfgd6546"},{"order":7,"image":"https://tintruyen.net/12390/fix-1/6.jpg?d=dfgd6546"},{"order":8,"image":"https://tintruyen.net/12390/fix-1/7.jpg?d=dfgd6546"},{"order":9,"image":"https://tintruyen.net/12390/fix-1/8.jpg?d=dfgd6546"},{"order":10,"image":"https://tintruyen.net/12390/fix-1/9.jpg?d=dfgd6546"},{"order":11,"image":"https://tintruyen.net/12390/fix-1/10.jpg?d=dfgd6546"},{"order":12,"image":"https://tintruyen.net/12390/fix-1/11.jpg?d=dfgd6546"},{"order":13,"image":"https://tintruyen.net/12390/fix-1/12.jpg?d=dfgd6546"},{"order":14,"image":"https://tintruyen.net/12390/fix-1/13.jpg?d=dfgd6546"},{"order":15,"image":"https://tintruyen.net/12390/fix-1/14.jpg?d=dfgd6546"},{"order":16,"image":"https://tintruyen.net/12390/fix-1/15.jpg?d=dfgd6546"},{"order":17,"image":"https://tintruyen.net/12390/fix-1/16.jpg?d=dfgd6546"},{"order":18,"image":"https://tintruyen.net/12390/fix-1/17.jpg?d=dfgd6546"},{"order":19,"image":"https://tintruyen.net/12390/fix-1/18.jpg?d=dfgd6546"},{"order":20,"image":"https://tintruyen.net/12390/fix-1/19.jpg?d=dfgd6546"},{"order":21,"image":"https://tintruyen.net/12390/fix-1/20.jpg?d=dfgd6546"},{"order":22,"image":"https://tintruyen.net/12390/fix-1/21.jpg?d=dfgd6546"},{"order":23,"image":"https://tintruyen.net/12390/fix-1/22.jpg?d=dfgd6546"},{"order":24,"image":"https://tintruyen.net/12390/fix-1/23.jpg?d=dfgd6546"},{"order":25,"image":"https://tintruyen.net/12390/fix-1/24.jpg?d=dfgd6546"},{"order":26,"image":"https://tintruyen.net/12390/fix-1/25.jpg?d=dfgd6546"},{"order":27,"image":"https://tintruyen.net/12390/fix-1/26.jpg?d=dfgd6546"},{"order":28,"image":"https://tintruyen.net/12390/fix-1/27.jpg?d=dfgd6546"},{"order":29,"image":"https://tintruyen.net/12390/fix-1/28.jpg?d=dfgd6546"},{"order":30,"image":"https://tintruyen.net/12390/fix-1/29.jpg?d=dfgd6546"},{"order":31,"image":"https://tintruyen.net/12390/fix-1/30.jpg?d=dfgd6546"},{"order":32,"image":"https://tintruyen.net/12390/fix-1/31.jpg?d=dfgd6546"},{"order":33,"image":"https://tintruyen.net/12390/fix-1/32.jpg?d=dfgd6546"},{"order":34,"image":"https://tintruyen.net/12390/fix-1/33.jpg?d=dfgd6546"},{"order":35,"image":"https://tintruyen.net/12390/fix-1/34.jpg?d=dfgd6546"},{"order":36,"image":"https://tintruyen.net/12390/fix-1/35.jpg?d=dfgd6546"},{"order":37,"image":"https://tintruyen.net/12390/fix-1/36.jpg?d=dfgd6546"},{"order":38,"image":"https://tintruyen.net/12390/fix-1/37.jpg?d=dfgd6546"},{"order":39,"image":"https://tintruyen.net/12390/fix-1/38.jpg?d=dfgd6546"},{"order":40,"image":"https://tintruyen.net/12390/fix-1/39.jpg?d=dfgd6546"},{"order":41,"image":"https://tintruyen.net/12390/fix-1/40.jpg?d=dfgd6546"},{"order":42,"image":"https://tintruyen.net/12390/fix-1/41.jpg?d=dfgd6546"},{"order":43,"image":"https://tintruyen.net/12390/fix-1/42.jpg?d=dfgd6546"},{"order":44,"image":"https://tintruyen.net/12390/fix-1/43.jpg?d=dfgd6546"},{"order":45,"image":"https://tintruyen.net/12390/fix-1/44.jpg?d=dfgd6546"},{"order":46,"image":"https://tintruyen.net/12390/fix-1/45.jpg?d=dfgd6546"},{"order":47,"image":"https://tintruyen.net/12390/fix-1/46.jpg?d=dfgd6546"},{"order":48,"image":"https://tintruyen.net/12390/fix-1/47.jpg?d=dfgd6546"},{"order":49,"image":"https://tintruyen.net/12390/fix-1/48.jpg?d=dfgd6546"},{"order":50,"image":"https://tintruyen.net/12390/fix-1/49.jpg?d=dfgd6546"},{"order":51,"image":"https://tintruyen.net/12390/fix-1/50.jpg?d=dfgd6546"},{"order":52,"image":"https://tintruyen.net/12390/fix-1/51.jpg?d=dfgd6546"},{"order":53,"image":"https://tintruyen.net/12390/fix-1/52.jpg?d=dfgd6546"}]}]}